{
    "Changes": [
        {
            "LogName": "Loading livestock slime assets",
            "Action": "Load",
            "Target": "{{ModId}}/pink_slime, {{ModId}}/pink_slime_shop_texture, {{ModId}}/tabby_slime, {{ModId}}/tabby_slime_shop_texture, {{ModId}}/phosphor_slime, {{ModId}}/phosphor_slime_shop_texture, {{ModId}}/honey_slime, {{ModId}}/honey_slime_shop_texture, {{ModId}}/hunter_slime, {{ModId}}/hunter_slime_shop_texture, {{ModId}}/quantum_slime, {{ModId}}/quantum_slime_shop_texture, {{ModId}}/dervish_slime, {{ModId}}/dervish_slime_shop_texture, {{ModId}}/tangle_slime, {{ModId}}/tangle_slime_shop_texture, {{ModId}}/saber_slime, {{ModId}}/saber_slime_shop_texture, {{ModId}}/rock_slime, {{ModId}}/rock_slime_shop_texture, {{ModId}}/rad_slime, {{ModId}}/rad_slime_shop_texture, {{ModId}}/boom_slime, {{ModId}}/boom_slime_shop_texture, {{ModId}}/crystal_slime, {{ModId}}/crystal_slime_shop_texture, {{ModId}}/mosaic_slime, {{ModId}}/mosaic_slime_shop_texture",
            "FromFile": "assets/slimes/{{TargetWithoutPath}}.png"
        },
        {
            "LogName": "Editing data for livestock Slimes",
            "Action": "EditData",
            "Target": "Data/FarmAnimals",
            "Entries": {
                "{{ModId}}.Pink_Slime": {
                    "DisplayName": "{{i18n: pink_slime.name}}",
                    "House": "Coop",
                    "Gender": "MaleOrFemale",
                    "PurchasePrice": "{{Pink Slime Purchase Price}}",
                    "SellPrice": "{{Pink Slime Sell Price}}",
                    "ShopTexture": "{{ModID}}/pink_slime_shop_texture",
                    "ShopSourceRect": {
                        "X": 0,
                        "Y": 0,
                        "Width": 32,
                        "Height": 16
                    },
                    "ShopDisplayName": "{{i18n: pink_slime.name}}",
                    "ShopDescription": "{{i18n: pink_slime.description |days={{Slime Days To Produce}}}}",
                    "ShopMissingBuildingDescription": "[LocalizedText Strings\\StringsFromCSFiles:Utility.cs.5926]",
                    "RequiredBuilding": "Coop",
                    "UnlockCondition": null,
                    "EggItemIds": [
                        "{{ModId}}.Pink_Plort"
                    ],
                    "IncubationTime": -1,
                    "IncubatorParentSheetOffset": 1,
                    "BirthText": "{{i18n: pink_slime.birth}}",
                    "DaysToMature": "{{Slime Days To Mature}}",
                    "CanGetPregnant": false,
                    "DaysToProduce": "{{Slime Days To Produce}}",
                    "HarvestType": 0,
                    "HarvestTool": null,
                    "ProduceOnMature": false,
                    "FriendshipForFasterProduce": -1,
                    "DeluxeProduceMinimumFriendship": 200,
                    "DeluxeProduceCareDivisor": 1200.0,
                    "DeluxeProduceLuckMultiplier": 0.0,
                    "ProfessionForHappinessBoost": 2,
                    "ProfessionForQualityBoost": 2,
                    "ProfessionForFasterProduce": -1,
                    "Sound": "slime",
                    "BabySound": "slime",
                    "Texture": "{{ModID}}/pink_slime",
                    "HarvestedTexture": null,
                    "BabyTexture": "{{ModID}}/pink_slime",
                    "UseFlippedRightForLeft": true,
                    "SpriteWidth": 16,
                    "SpriteHeight": 16,
                    "Skins": null,
                    "ShadowWhenBabySwims": null,
                    "ShadowWhenBaby": null,
                    "ShadowWhenAdultSwims": null,
                    "ShadowWhenAdult": null,
                    "CanSwim": false,
                    "BabiesFollowAdults": true,
                    "GrassEatAmount": 2,
                    "HappinessDrain": 7,
                    "ShowInSummitCredits": true,
                    "CustomFields": null
                },
                "{{ModId}}.Tabby_Slime": {
                    "DisplayName": "{{i18n: tabby_slime.name}}",
                    "House": "Coop",
                    "Gender": "MaleOrFemale",
                    "PurchasePrice": "{{Tabby Slime Purchase Price}}",
                    "SellPrice": "{{Tabby Slime Sell Price}}",
                    "ShopTexture": "{{ModID}}/tabby_slime_shop_texture",
                    "ShopSourceRect": {
                        "X": 0,
                        "Y": 0,
                        "Width": 32,
                        "Height": 16
                    },
                    "ShopDisplayName": "{{i18n: tabby_slime.name}}",
                    "ShopDescription": "{{i18n: tabby_slime.description |days={{Slime Days To Produce}}}}",
                    "ShopMissingBuildingDescription": "[LocalizedText Strings\\StringsFromCSFiles:Utility.cs.5926]",
                    "RequiredBuilding": "Coop",
                    "UnlockCondition": null,
                    "EggItemIds": [
                        "{{ModId}}.Tabby_Plort"
                    ],
                    "IncubationTime": -1,
                    "IncubatorParentSheetOffset": 1,
                    "BirthText": "{{i18n: tabby_slime.birth}}",
                    "DaysToMature": "{{Slime Days To Mature}}",
                    "CanGetPregnant": false,
                    "DaysToProduce": "{{Slime Days To Produce}}",
                    "HarvestType": 0,
                    "HarvestTool": null,
                    "ProduceItemIds": [
                        {
                            "Id": "Default",
                            "Condition": null,
                            "MinimumFriendship": 0,
                            "ItemId": "{{ModId}}.Tabby_Plort"
                        }
                    ],
                    "DeluxeProduceItemIds": [
                        {
                            "Id": "Default",
                            "Condition": null,
                            "MinimumFriendship": 0,
                            "ItemId": "{{Random: 132, 136, 138, 139, 140, 141, 142, 143, 144, 145, 153, 167, 168, 169, 170, 171, 172, 269, 424, 444, 446, 698, 699, 700, 702, 704, 706, 707, 720, 722, 767}}"
                        }
                    ],
                    "ProduceOnMature": false,
                    "FriendshipForFasterProduce": -1,
                    "DeluxeProduceMinimumFriendship": 200,
                    "DeluxeProduceCareDivisor": 1200.0,
                    "DeluxeProduceLuckMultiplier": 0.0,
                    "ProfessionForHappinessBoost": 2,
                    "ProfessionForQualityBoost": 2,
                    "ProfessionForFasterProduce": -1,
                    "Sound": "slime",
                    "BabySound": "slime",
                    "Texture": "{{ModID}}/tabby_slime",
                    "HarvestedTexture": null,
                    "BabyTexture": "{{ModID}}/tabby_slime",
                    "UseFlippedRightForLeft": true,
                    "SpriteWidth": 16,
                    "SpriteHeight": 16,
                    "Skins": null,
                    "ShadowWhenBabySwims": null,
                    "ShadowWhenBaby": null,
                    "ShadowWhenAdultSwims": null,
                    "ShadowWhenAdult": null,
                    "CanSwim": false,
                    "BabiesFollowAdults": true,
                    "GrassEatAmount": 2,
                    "HappinessDrain": 7,
                    "ShowInSummitCredits": true,
                    "CustomFields": null
                },
                "{{ModId}}.Phosphor_Slime": {
                    "DisplayName": "{{i18n: phosphor_slime.name}}",
                    "House": "Coop",
                    "Gender": "MaleOrFemale",
                    "PurchasePrice": "{{Phosphor Slime Purchase Price}}",
                    "SellPrice": "{{Phosphor Slime Sell Price}}",
                    "ShopTexture": "{{ModID}}/phosphor_slime_shop_texture",
                    "ShopSourceRect": {
                        "X": 0,
                        "Y": 0,
                        "Width": 32,
                        "Height": 16
                    },
                    "ShopDisplayName": "{{i18n: phosphor_slime.name}}",
                    "ShopDescription": "{{i18n: phosphor_slime.description |days={{Slime Days To Produce}}}}",
                    "ShopMissingBuildingDescription": "[LocalizedText Strings\\StringsFromCSFiles:Utility.cs.5926]",
                    "RequiredBuilding": "Coop",
                    "UnlockCondition": null,
                    "EggItemIds": [
                        "{{ModId}}.Phosphor_Plort"
                    ],
                    "IncubationTime": -1,
                    "IncubatorParentSheetOffset": 1,
                    "BirthText": "{{i18n: phosphor_slime.birth}}",
                    "DaysToMature": "{{Slime Days To Mature}}",
                    "CanGetPregnant": false,
                    "DaysToProduce": "{{Slime Days To Produce}}",
                    "HarvestType": 0,
                    "HarvestTool": null,
                    "ProduceItemIds": [
                        {
                            "Id": "Default",
                            "Condition": null,
                            "MinimumFriendship": 0,
                            "ItemId": "{{ModId}}.Phosphor_Plort"
                        }
                    ],
                    "DeluxeProduceItemIds": [
                        {
                            "Id": "Default",
                            "Condition": null,
                            "MinimumFriendship": 0,
                            "ItemId": "768"
                        }
                    ],
                    "ProduceOnMature": false,
                    "FriendshipForFasterProduce": -1,
                    "DeluxeProduceMinimumFriendship": 200,
                    "DeluxeProduceCareDivisor": 1200.0,
                    "DeluxeProduceLuckMultiplier": 0.0,
                    "ProfessionForHappinessBoost": 2,
                    "ProfessionForQualityBoost": 2,
                    "ProfessionForFasterProduce": -1,
                    "Sound": "slime",
                    "BabySound": "slime",
                    "Texture": "{{ModID}}/phosphor_slime",
                    "HarvestedTexture": null,
                    "BabyTexture": "{{ModID}}/phosphor_slime",
                    "UseFlippedRightForLeft": true,
                    "SpriteWidth": 16,
                    "SpriteHeight": 16,
                    "Skins": null,
                    "ShadowWhenBabySwims": null,
                    "ShadowWhenBaby": null,
                    "ShadowWhenAdultSwims": null,
                    "ShadowWhenAdult": null,
                    "CanSwim": false,
                    "BabiesFollowAdults": true,
                    "GrassEatAmount": 2,
                    "HappinessDrain": 7,
                    "ShowInSummitCredits": true,
                    "CustomFields": null
                },
                "{{ModId}}.Honey_Slime": {
                    "DisplayName": "{{i18n: honey_slime.name}}",
                    "House": "Coop",
                    "Gender": "MaleOrFemale",
                    "PurchasePrice": "{{Honey Slime Purchase Price}}",
                    "SellPrice": "{{Honey Slime Sell Price}}",
                    "ShopTexture": "{{ModID}}/honey_slime_shop_texture",
                    "ShopSourceRect": {
                        "X": 0,
                        "Y": 0,
                        "Width": 32,
                        "Height": 16
                    },
                    "ShopDisplayName": "{{i18n: honey_slime.name}}",
                    "ShopDescription": "{{i18n: honey_slime.description |days={{Slime Days To Produce}}}}",
                    "ShopMissingBuildingDescription": "[LocalizedText Strings\\StringsFromCSFiles:Utility.cs.5926]",
                    "RequiredBuilding": "Coop",
                    "UnlockCondition": "PLAYER_VISITED_LOCATION Current Woods",
                    "EggItemIds": [
                        "{{ModId}}.Honey_Plort"
                    ],
                    "IncubationTime": -1,
                    "IncubatorParentSheetOffset": 1,
                    "BirthText": "{{i18n: honey_slime.birth}}",
                    "DaysToMature": "{{Slime Days To Mature}}",
                    "CanGetPregnant": false,
                    "DaysToProduce": "{{Slime Days To Produce}}",
                    "HarvestType": 0,
                    "HarvestTool": null,
                    "ProduceItemIds": [
                        {
                            "Id": "Default",
                            "Condition": null,
                            "MinimumFriendship": 0,
                            "ItemId": "{{ModId}}.Honey_Plort"
                        }
                    ],
                    "DeluxeProduceItemIds": [
                        {
                            "Id": "Default",
                            "Condition": null,
                            "MinimumFriendship": 0,
                            "ItemId": "340"
                        }
                    ],
                    "ProduceOnMature": false,
                    "FriendshipForFasterProduce": -1,
                    "DeluxeProduceMinimumFriendship": 200,
                    "DeluxeProduceCareDivisor": 1200.0,
                    "DeluxeProduceLuckMultiplier": 0.0,
                    "ProfessionForHappinessBoost": 2,
                    "ProfessionForQualityBoost": 2,
                    "ProfessionForFasterProduce": -1,
                    "Sound": "slime",
                    "BabySound": "slime",
                    "Texture": "{{ModID}}/honey_slime",
                    "HarvestedTexture": null,
                    "BabyTexture": "{{ModID}}/honey_slime",
                    "UseFlippedRightForLeft": true,
                    "SpriteWidth": 16,
                    "SpriteHeight": 16,
                    "Skins": null,
                    "ShadowWhenBabySwims": null,
                    "ShadowWhenBaby": null,
                    "ShadowWhenAdultSwims": null,
                    "ShadowWhenAdult": null,
                    "CanSwim": false,
                    "BabiesFollowAdults": true,
                    "GrassEatAmount": 2,
                    "HappinessDrain": 7,
                    "ShowInSummitCredits": true,
                    "CustomFields": null
                },
                "{{ModId}}.Hunter_Slime": {
                    "DisplayName": "{{i18n: hunter_slime.name}}",
                    "House": "Coop",
                    "Gender": "MaleOrFemale",
                    "PurchasePrice": "{{Hunter Slime Purchase Price}}",
                    "SellPrice": "{{Hunter Slime Sell Price}}",
                    "ShopTexture": "{{ModID}}/hunter_slime_shop_texture",
                    "ShopSourceRect": {
                        "X": 0,
                        "Y": 0,
                        "Width": 32,
                        "Height": 16
                    },
                    "ShopDisplayName": "{{i18n: hunter_slime.name}}",
                    "ShopDescription": "{{i18n: hunter_slime.description |days={{Slime Days To Produce}}}}",
                    "ShopMissingBuildingDescription": "[LocalizedText Strings\\StringsFromCSFiles:Utility.cs.5926]",
                    "RequiredBuilding": "Coop",
                    "UnlockCondition": "PLAYER_VISITED_LOCATION Current Woods",
                    "EggItemIds": [
                        "{{ModId}}.Hunter_Plort"
                    ],
                    "IncubationTime": -1,
                    "IncubatorParentSheetOffset": 1,
                    "BirthText": "{{i18n: hunter_slime.birth}}",
                    "DaysToMature": "{{Slime Days To Mature}}",
                    "CanGetPregnant": false,
                    "DaysToProduce": "{{Slime Days To Produce}}",
                    "HarvestType": 0,
                    "HarvestTool": null,
                    "ProduceItemIds": [
                        {
                            "Id": "Default",
                            "Condition": null,
                            "MinimumFriendship": 0,
                            "ItemId": "{{ModId}}.Hunter_Plort"
                        }
                    ],
                    "DeluxeProduceItemIds": [
                        {
                            "Id": "Default",
                            "Condition": null,
                            "MinimumFriendship": 0,
                            "ItemId": "{{Random: 174, 176, 180, 182, 184, 186, 426, 436, 438, 440, 442, 444, 446}}"
                        }
                    ],
                    "ProduceOnMature": false,
                    "FriendshipForFasterProduce": -1,
                    "DeluxeProduceMinimumFriendship": 200,
                    "DeluxeProduceCareDivisor": 1200.0,
                    "DeluxeProduceLuckMultiplier": 0.0,
                    "ProfessionForHappinessBoost": 2,
                    "ProfessionForQualityBoost": 2,
                    "ProfessionForFasterProduce": -1,
                    "Sound": "slime",
                    "BabySound": "slime",
                    "Texture": "{{ModID}}/hunter_slime",
                    "HarvestedTexture": null,
                    "BabyTexture": "{{ModID}}/hunter_slime",
                    "UseFlippedRightForLeft": true,
                    "SpriteWidth": 16,
                    "SpriteHeight": 16,
                    "Skins": null,
                    "ShadowWhenBabySwims": null,
                    "ShadowWhenBaby": null,
                    "ShadowWhenAdultSwims": null,
                    "ShadowWhenAdult": null,
                    "CanSwim": false,
                    "BabiesFollowAdults": true,
                    "GrassEatAmount": 2,
                    "HappinessDrain": 7,
                    "ShowInSummitCredits": true,
                    "CustomFields": null
                },
                "{{ModId}}.Dervish_Slime": {
                    "DisplayName": "{{i18n: dervish_slime.name}}",
                    "House": "Coop",
                    "Gender": "MaleOrFemale",
                    "PurchasePrice": "{{Dervish Slime Purchase Price}}",
                    "SellPrice": "{{Dervish Slime Sell Price}}",
                    "ShopTexture": "{{ModID}}/dervish_slime_shop_texture",
                    "ShopSourceRect": {
                        "X": 0,
                        "Y": 0,
                        "Width": 32,
                        "Height": 16
                    },
                    "ShopDisplayName": "{{i18n: dervish_slime.name}}",
                    "ShopDescription": "{{i18n: dervish_slime.description |days={{Slime Days To Produce}}}}",
                    "ShopMissingBuildingDescription": "[LocalizedText Strings\\StringsFromCSFiles:Utility.cs.5926]",
                    "RequiredBuilding": "Coop",
                    "UnlockCondition": "LOCATION_ACCESSIBLE Desert",
                    "EggItemIds": [
                        "{{ModId}}.Dervish_Plort"
                    ],
                    "IncubationTime": -1,
                    "IncubatorParentSheetOffset": 1,
                    "BirthText": "{{i18n: dervish_slime.birth}}",
                    "DaysToMature": "{{Slime Days To Mature}}",
                    "CanGetPregnant": false,
                    "DaysToProduce": "{{Slime Days To Produce}}",
                    "HarvestType": 0,
                    "HarvestTool": null,
                    "ProduceItemIds": [
                        {
                            "Id": "Default",
                            "Condition": null,
                            "MinimumFriendship": 0,
                            "ItemId": "{{ModId}}.Dervish_Plort"
                        }
                    ],
                    "DeluxeProduceItemIds": [
                        {
                            "Id": "Default",
                            "Condition": null,
                            "MinimumFriendship": 0,
                            "ItemId": "{{Random: 767, 787}}"
                        }
                    ],
                    "ProduceOnMature": false,
                    "FriendshipForFasterProduce": -1,
                    "DeluxeProduceMinimumFriendship": 200,
                    "DeluxeProduceCareDivisor": 1200.0,
                    "DeluxeProduceLuckMultiplier": 0.0,
                    "ProfessionForHappinessBoost": 2,
                    "ProfessionForQualityBoost": 2,
                    "ProfessionForFasterProduce": -1,
                    "Sound": "slime",
                    "BabySound": "slime",
                    "Texture": "{{ModID}}/dervish_slime",
                    "HarvestedTexture": null,
                    "BabyTexture": "{{ModID}}/dervish_slime",
                    "UseFlippedRightForLeft": true,
                    "SpriteWidth": 16,
                    "SpriteHeight": 16,
                    "Skins": null,
                    "ShadowWhenBabySwims": null,
                    "ShadowWhenBaby": null,
                    "ShadowWhenAdultSwims": null,
                    "ShadowWhenAdult": null,
                    "CanSwim": false,
                    "BabiesFollowAdults": true,
                    "GrassEatAmount": 2,
                    "HappinessDrain": 7,
                    "ShowInSummitCredits": true,
                    "CustomFields": null
                },
                "{{ModId}}.Tangle_Slime": {
                    "DisplayName": "{{i18n: tangle_slime.name}}",
                    "House": "Coop",
                    "Gender": "MaleOrFemale",
                    "PurchasePrice": "{{Tangle Slime Purchase Price}}",
                    "SellPrice": "{{Tangle Slime Sell Price}}",
                    "ShopTexture": "{{ModID}}/tangle_slime_shop_texture",
                    "ShopSourceRect": {
                        "X": 0,
                        "Y": 0,
                        "Width": 32,
                        "Height": 16
                    },
                    "ShopDisplayName": "{{i18n: tangle_slime.name}}",
                    "ShopDescription": "{{i18n: tangle_slime.description |days={{Slime Days To Produce}}}}",
                    "ShopMissingBuildingDescription": "[LocalizedText Strings\\StringsFromCSFiles:Utility.cs.5926]",
                    "RequiredBuilding": "Coop",
                    "UnlockCondition": "LOCATION_ACCESSIBLE Desert",
                    "EggItemIds": [
                        "{{ModId}}.Tangle_Plort"
                    ],
                    "IncubationTime": -1,
                    "IncubatorParentSheetOffset": 1,
                    "BirthText": "{{i18n: tangle_slime.birth}}",
                    "DaysToMature": "{{Slime Days To Mature}}",
                    "CanGetPregnant": false,
                    "DaysToProduce": "{{Slime Days To Produce}}",
                    "HarvestType": 0,
                    "HarvestTool": null,
                    "ProduceOnMature": false,
                    "FriendshipForFasterProduce": -1,
                    "DeluxeProduceMinimumFriendship": 200,
                    "DeluxeProduceCareDivisor": 1200.0,
                    "DeluxeProduceLuckMultiplier": 0.0,
                    "ProfessionForHappinessBoost": 2,
                    "ProfessionForQualityBoost": 2,
                    "ProfessionForFasterProduce": -1,
                    "Sound": "slime",
                    "BabySound": "slime",
                    "Texture": "{{ModID}}/tangle_slime",
                    "HarvestedTexture": null,
                    "BabyTexture": "{{ModID}}/tangle_slime",
                    "UseFlippedRightForLeft": true,
                    "SpriteWidth": 16,
                    "SpriteHeight": 16,
                    "Skins": null,
                    "ShadowWhenBabySwims": null,
                    "ShadowWhenBaby": null,
                    "ShadowWhenAdultSwims": null,
                    "ShadowWhenAdult": null,
                    "CanSwim": false,
                    "BabiesFollowAdults": true,
                    "GrassEatAmount": 2,
                    "HappinessDrain": 7,
                    "ShowInSummitCredits": true,
                    "CustomFields": null
                },
                "{{ModId}}.Saber_Slime": {
                    "DisplayName": "{{i18n: saber_slime.name}}",
                    "House": "Coop",
                    "Gender": "MaleOrFemale",
                    "PurchasePrice": "{{Saber Slime Purchase Price}}",
                    "SellPrice": "{{Saber Slime Sell Price}}",
                    "ShopTexture": "{{ModID}}/saber_slime_shop_texture",
                    "ShopSourceRect": {
                        "X": 0,
                        "Y": 0,
                        "Width": 32,
                        "Height": 16
                    },
                    "ShopDisplayName": "{{i18n: saber_slime.name}}",
                    "ShopDescription": "{{i18n: saber_slime.description |days={{Slime Days To Produce}}}}",
                    "ShopMissingBuildingDescription": "[LocalizedText Strings\\StringsFromCSFiles:Utility.cs.5926]",
                    "RequiredBuilding": "Coop",
                    "UnlockCondition": "MUSEUM_DONATIONS 95 95 Arch Minerals",
                    "EggItemIds": [
                        "{{ModId}}.Saber_Plort"
                    ],
                    "IncubationTime": -1,
                    "IncubatorParentSheetOffset": 1,
                    "BirthText": "{{i18n: saber_slime.birth}}",
                    "DaysToMature": "{{Slime Days To Mature}}",
                    "CanGetPregnant": false,
                    "DaysToProduce": "{{Slime Days To Produce}}",
                    "HarvestType": 0,
                    "HarvestTool": null,
                    "ProduceItemIds": [
                        {
                            "Id": "Default",
                            "Condition": null,
                            "MinimumFriendship": 0,
                            "ItemId": "{{ModId}}.Saber_Plort"
                        }
                    ],
                    "DeluxeProduceItemIds": [
                        {
                            "Id": "Default",
                            "Condition": null,
                            "MinimumFriendship": 0,
                            "ItemId": "{{Random: 96, 97, 98, 99, 100, 101, 102, 103, 104, 105, 106, 107, 108, 109, 110, 111, 112, 113, 114, 115, 116, 117, 118, 119, 120, 121, 122, 123, 124, 125, 126, 127, 579, 580, 581, 582, 583, 584, 585, 586, 587, 588, 589, 881}}"
                        }
                    ],
                    "ProduceOnMature": false,
                    "FriendshipForFasterProduce": -1,
                    "DeluxeProduceMinimumFriendship": 200,
                    "DeluxeProduceCareDivisor": 1200.0,
                    "DeluxeProduceLuckMultiplier": 0.0,
                    "ProfessionForHappinessBoost": 2,
                    "ProfessionForQualityBoost": 2,
                    "ProfessionForFasterProduce": -1,
                    "Sound": "slime",
                    "BabySound": "slime",
                    "Texture": "{{ModID}}/saber_slime",
                    "HarvestedTexture": null,
                    "BabyTexture": "{{ModID}}/saber_slime",
                    "UseFlippedRightForLeft": true,
                    "SpriteWidth": 16,
                    "SpriteHeight": 16,
                    "Skins": null,
                    "ShadowWhenBabySwims": null,
                    "ShadowWhenBaby": null,
                    "ShadowWhenAdultSwims": null,
                    "ShadowWhenAdult": null,
                    "CanSwim": false,
                    "BabiesFollowAdults": true,
                    "GrassEatAmount": 2,
                    "HappinessDrain": 7,
                    "ShowInSummitCredits": true,
                    "CustomFields": null
                },
                "{{ModId}}.Rock_Slime": {
                    "DisplayName": "{{i18n: rock_slime.name}}",
                    "House": "Coop",
                    "Gender": "MaleOrFemale",
                    "PurchasePrice": "{{Rock Slime Purchase Price}}",
                    "SellPrice": "{{Rock Slime Sell Price}}",
                    "ShopTexture": "{{ModID}}/rock_slime_shop_texture",
                    "ShopSourceRect": {
                        "X": 0,
                        "Y": 0,
                        "Width": 32,
                        "Height": 16
                    },
                    "ShopDisplayName": "{{i18n: rock_slime.name}}",
                    "ShopDescription": "{{i18n: rock_slime.description |days={{Slime Days To Produce}}}}",
                    "ShopMissingBuildingDescription": "[LocalizedText Strings\\StringsFromCSFiles:Utility.cs.5926]",
                    "RequiredBuilding": "Coop",
                    "UnlockCondition": null,
                    "EggItemIds": [
                        "{{ModId}}.Rock_Plort"
                    ],
                    "IncubationTime": -1,
                    "IncubatorParentSheetOffset": 1,
                    "BirthText": "{{i18n: rock_slime.birth}}",
                    "DaysToMature": "{{Slime Days To Mature}}",
                    "CanGetPregnant": false,
                    "DaysToProduce": "{{Slime Days To Produce}}",
                    "HarvestType": 0,
                    "HarvestTool": null,
                    "ProduceItemIds": [
                        {
                            "Id": "Default",
                            "Condition": null,
                            "MinimumFriendship": 0,
                            "ItemId": "{{ModId}}.Rock_Plort"
                        }
                    ],
                    "DeluxeProduceItemIds": [
                        {
                            "Id": "Default",
                            "Condition": null,
                            "MinimumFriendship": 0,
                            "ItemId": "{{Random: 535, 536, 537, 749}}"
                        }
                    ],
                    "ProduceOnMature": false,
                    "FriendshipForFasterProduce": -1,
                    "DeluxeProduceMinimumFriendship": 200,
                    "DeluxeProduceCareDivisor": 1200.0,
                    "DeluxeProduceLuckMultiplier": 0.0,
                    "ProfessionForHappinessBoost": 2,
                    "ProfessionForQualityBoost": 2,
                    "ProfessionForFasterProduce": -1,
                    "Sound": "slime",
                    "BabySound": "slime",
                    "Texture": "{{ModID}}/rock_slime",
                    "HarvestedTexture": null,
                    "BabyTexture": "{{ModID}}/rock_slime",
                    "UseFlippedRightForLeft": true,
                    "SpriteWidth": 16,
                    "SpriteHeight": 16,
                    "Skins": null,
                    "ShadowWhenBabySwims": null,
                    "ShadowWhenBaby": null,
                    "ShadowWhenAdultSwims": null,
                    "ShadowWhenAdult": null,
                    "CanSwim": false,
                    "BabiesFollowAdults": true,
                    "GrassEatAmount": 2,
                    "HappinessDrain": 7,
                    "ShowInSummitCredits": true,
                    "CustomFields": null
                },
                "{{ModId}}.Rad_Slime": {
                    "DisplayName": "{{i18n: rad_slime.name}}",
                    "House": "Coop",
                    "Gender": "MaleOrFemale",
                    "PurchasePrice": "{{Rad Slime Purchase Price}}",
                    "SellPrice": "{{Rad Slime Sell Price}}",
                    "ShopTexture": "{{ModID}}/rad_slime_shop_texture",
                    "ShopSourceRect": {
                        "X": 0,
                        "Y": 0,
                        "Width": 32,
                        "Height": 16
                    },
                    "ShopDisplayName": "{{i18n: rad_slime.name}}",
                    "ShopDescription": "{{i18n: rad_slime.description |days={{Slime Days To Produce}}}}",
                    "ShopMissingBuildingDescription": "[LocalizedText Strings\\StringsFromCSFiles:Utility.cs.5926]",
                    "RequiredBuilding": "Coop",
                    "UnlockCondition": "MINE_LOWEST_LEVEL_REACHED 100 120",
                    "EggItemIds": [
                        "{{ModId}}.Rad_Plort"
                    ],
                    "IncubationTime": -1,
                    "IncubatorParentSheetOffset": 1,
                    "BirthText": "{{i18n: rad_slime.birth}}",
                    "DaysToMature": "{{Slime Days To Mature}}",
                    "CanGetPregnant": false,
                    "DaysToProduce": "{{Slime Days To Produce}}",
                    "HarvestType": 0,
                    "HarvestTool": null,
                    "ProduceItemIds": [
                        {
                            "Id": "Default",
                            "Condition": null,
                            "MinimumFriendship": 0,
                            "ItemId": "{{ModId}}.Rad_Plort"
                        }
                    ],
                    "DeluxeProduceItemIds": [
                        {
                            "Id": "Default",
                            "Condition": null,
                            "MinimumFriendship": 0,
                            "ItemId": "909"
                        }
                    ],
                    "ProduceOnMature": false,
                    "FriendshipForFasterProduce": -1,
                    "DeluxeProduceMinimumFriendship": 200,
                    "DeluxeProduceCareDivisor": 1200.0,
                    "DeluxeProduceLuckMultiplier": 0.0,
                    "ProfessionForHappinessBoost": 2,
                    "ProfessionForQualityBoost": 2,
                    "ProfessionForFasterProduce": -1,
                    "Sound": "slime",
                    "BabySound": "slime",
                    "Texture": "{{ModID}}/rad_slime",
                    "HarvestedTexture": null,
                    "BabyTexture": "{{ModID}}/rad_slime",
                    "UseFlippedRightForLeft": true,
                    "SpriteWidth": 16,
                    "SpriteHeight": 16,
                    "Skins": null,
                    "ShadowWhenBabySwims": null,
                    "ShadowWhenBaby": null,
                    "ShadowWhenAdultSwims": null,
                    "ShadowWhenAdult": null,
                    "CanSwim": false,
                    "BabiesFollowAdults": true,
                    "GrassEatAmount": 2,
                    "HappinessDrain": 7,
                    "ShowInSummitCredits": true,
                    "CustomFields": null
                },
                "{{ModId}}.Boom_Slime": {
                    "DisplayName": "{{i18n: boom_slime.name}}",
                    "House": "Coop",
                    "Gender": "MaleOrFemale",
                    "PurchasePrice": "{{Boom Slime Purchase Price}}",
                    "SellPrice": "{{Boom Slime Sell Price}}",
                    "ShopTexture": "{{ModID}}/boom_slime_shop_texture",
                    "ShopSourceRect": {
                        "X": 0,
                        "Y": 0,
                        "Width": 32,
                        "Height": 16
                    },
                    "ShopDisplayName": "{{i18n: boom_slime.name}}",
                    "ShopDescription": "{{i18n: boom_slime.description |days={{Slime Days To Produce}}}}",
                    "ShopMissingBuildingDescription": "[LocalizedText Strings\\StringsFromCSFiles:Utility.cs.5926]",
                    "RequiredBuilding": "Coop",
                    "UnlockCondition": "MINE_LOWEST_LEVEL_REACHED 100 120",
                    "EggItemIds": [
                        "{{ModId}}.Boom_Plort"
                    ],
                    "IncubationTime": -1,
                    "IncubatorParentSheetOffset": 1,
                    "BirthText": "{{i18n: boom_slime.birth}}",
                    "DaysToMature": "{{Slime Days To Mature}}",
                    "CanGetPregnant": false,
                    "DaysToProduce": "{{Slime Days To Produce}}",
                    "HarvestType": 0,
                    "HarvestTool": null,
                    "ProduceItemIds": [
                        {
                            "Id": "Default",
                            "Condition": null,
                            "MinimumFriendship": 0,
                            "ItemId": "{{ModId}}.Boom_Plort"
                        }
                    ],
                    "DeluxeProduceItemIds": [
                        {
                            "Id": "Default",
                            "Condition": null,
                            "MinimumFriendship": 0,
                            "ItemId": "{{Random: 286, 287, 288}}"
                        }
                    ],
                    "ProduceOnMature": false,
                    "FriendshipForFasterProduce": -1,
                    "DeluxeProduceMinimumFriendship": 200,
                    "DeluxeProduceCareDivisor": 1200.0,
                    "DeluxeProduceLuckMultiplier": 0.0,
                    "ProfessionForHappinessBoost": 2,
                    "ProfessionForQualityBoost": 2,
                    "ProfessionForFasterProduce": -1,
                    "Sound": "slime",
                    "BabySound": "slime",
                    "Texture": "{{ModID}}/boom_slime",
                    "HarvestedTexture": null,
                    "BabyTexture": "{{ModID}}/boom_slime",
                    "UseFlippedRightForLeft": true,
                    "SpriteWidth": 16,
                    "SpriteHeight": 16,
                    "Skins": null,
                    "ShadowWhenBabySwims": null,
                    "ShadowWhenBaby": null,
                    "ShadowWhenAdultSwims": null,
                    "ShadowWhenAdult": null,
                    "CanSwim": false,
                    "BabiesFollowAdults": true,
                    "GrassEatAmount": 2,
                    "HappinessDrain": 7,
                    "ShowInSummitCredits": true,
                    "CustomFields": null
                },
                "{{ModId}}.Crystal_Slime": {
                    "DisplayName": "{{i18n: crystal_slime.name}}",
                    "House": "Coop",
                    "Gender": "MaleOrFemale",
                    "PurchasePrice": "{{Crystal Slime Purchase Price}}",
                    "SellPrice": "{{Crystal Slime Sell Price}}",
                    "ShopTexture": "{{ModID}}/crystal_slime_shop_texture",
                    "ShopSourceRect": {
                        "X": 0,
                        "Y": 0,
                        "Width": 32,
                        "Height": 16
                    },
                    "ShopDisplayName": "{{i18n: crystal_slime.name}}",
                    "ShopDescription": "{{i18n: crystal_slime.description |days={{Slime Days To Produce}}}}",
                    "ShopMissingBuildingDescription": "[LocalizedText Strings\\StringsFromCSFiles:Utility.cs.5926]",
                    "RequiredBuilding": "Coop",
                    "UnlockCondition": "MINE_LOWEST_LEVEL_REACHED 100 120",
                    "EggItemIds": [
                        "{{ModId}}.Crystal_Plort"
                    ],
                    "IncubationTime": -1,
                    "IncubatorParentSheetOffset": 1,
                    "BirthText": "{{i18n: crystal_slime.birth}}",
                    "DaysToMature": "{{Slime Days To Mature}}",
                    "CanGetPregnant": false,
                    "DaysToProduce": "{{Slime Days To Produce}}",
                    "HarvestType": 0,
                    "HarvestTool": null,
                    "ProduceItemIds": [
                        {
                            "Id": "Default",
                            "Condition": null,
                            "MinimumFriendship": 0,
                            "ItemId": "{{ModId}}.Crystal_Plort"
                        }
                    ],
                    "DeluxeProduceItemIds": [
                        {
                            "Id": "Default",
                            "Condition": null,
                            "MinimumFriendship": 0,
                            "ItemId": "{{Random: 80, 82}}"
                        }
                    ],
                    "ProduceOnMature": false,
                    "FriendshipForFasterProduce": -1,
                    "DeluxeProduceMinimumFriendship": 200,
                    "DeluxeProduceCareDivisor": 1200.0,
                    "DeluxeProduceLuckMultiplier": 0.0,
                    "ProfessionForHappinessBoost": 2,
                    "ProfessionForQualityBoost": 2,
                    "ProfessionForFasterProduce": -1,
                    "Sound": "slime",
                    "BabySound": "slime",
                    "Texture": "{{ModID}}/crystal_slime",
                    "HarvestedTexture": null,
                    "BabyTexture": "{{ModID}}/crystal_slime",
                    "UseFlippedRightForLeft": true,
                    "SpriteWidth": 16,
                    "SpriteHeight": 16,
                    "Skins": null,
                    "ShadowWhenBabySwims": null,
                    "ShadowWhenBaby": null,
                    "ShadowWhenAdultSwims": null,
                    "ShadowWhenAdult": null,
                    "CanSwim": false,
                    "BabiesFollowAdults": true,
                    "GrassEatAmount": 2,
                    "HappinessDrain": 7,
                    "ShowInSummitCredits": true,
                    "CustomFields": null
                },
                "{{ModId}}.Mosaic_Slime": {
                    "DisplayName": "{{i18n: mosaic_slime.name}}",
                    "House": "Coop",
                    "Gender": "MaleOrFemale",
                    "PurchasePrice": "{{Mosaic Slime Purchase Price}}",
                    "SellPrice": "{{Mosaic Slime Sell Price}}",
                    "ShopTexture": "{{ModID}}/mosaic_slime_shop_texture",
                    "ShopSourceRect": {
                        "X": 0,
                        "Y": 0,
                        "Width": 32,
                        "Height": 16
                    },
                    "ShopDisplayName": "{{i18n: mosaic_slime.name}}",
                    "ShopDescription": "{{i18n: mosaic_slime.description |days={{Slime Days To Produce}}}}",
                    "ShopMissingBuildingDescription": "[LocalizedText Strings\\StringsFromCSFiles:Utility.cs.5926]",
                    "RequiredBuilding": "Coop",
                    "UnlockCondition": "LOCATION_ACCESSIBLE Desert",
                    "EggItemIds": [
                        "{{ModId}}.Mosaic_Plort"
                    ],
                    "IncubationTime": -1,
                    "IncubatorParentSheetOffset": 1,
                    "BirthText": "{{i18n: mosaic_slime.birth}}",
                    "DaysToMature": "{{Slime Days To Mature}}",
                    "CanGetPregnant": false,
                    "DaysToProduce": "{{Slime Days To Produce}}",
                    "HarvestType": 0,
                    "HarvestTool": null,
                    "ProduceItemIds": [
                        {
                            "Id": "Default",
                            "Condition": null,
                            "MinimumFriendship": 0,
                            "ItemId": "{{ModId}}.Mosaic_Plort"
                        }
                    ],
                    "DeluxeProduceItemIds": [
                        {
                            "Id": "Default",
                            "Condition": null,
                            "MinimumFriendship": 0,
                            "ItemId": "{{Random: 60, 62, 64, 66, 68, 70, 72}}"
                        }
                    ],
                    "ProduceOnMature": false,
                    "FriendshipForFasterProduce": -1,
                    "DeluxeProduceMinimumFriendship": 200,
                    "DeluxeProduceCareDivisor": 1200.0,
                    "DeluxeProduceLuckMultiplier": 0.0,
                    "ProfessionForHappinessBoost": 2,
                    "ProfessionForQualityBoost": 2,
                    "ProfessionForFasterProduce": -1,
                    "Sound": "slime",
                    "BabySound": "slime",
                    "Texture": "{{ModID}}/mosaic_slime",
                    "HarvestedTexture": null,
                    "BabyTexture": "{{ModID}}/mosaic_slime",
                    "UseFlippedRightForLeft": true,
                    "SpriteWidth": 16,
                    "SpriteHeight": 16,
                    "Skins": null,
                    "ShadowWhenBabySwims": null,
                    "ShadowWhenBaby": null,
                    "ShadowWhenAdultSwims": null,
                    "ShadowWhenAdult": null,
                    "CanSwim": false,
                    "BabiesFollowAdults": true,
                    "GrassEatAmount": 2,
                    "HappinessDrain": 7,
                    "ShowInSummitCredits": true,
                    "CustomFields": null
                },
                "{{ModId}}.Quantum_Slime": {
                    "DisplayName": "{{i18n: quantum_slime.name}}",
                    "House": "Coop",
                    "Gender": "MaleOrFemale",
                    "PurchasePrice": "{{Quantum Slime Purchase Price}}",
                    "SellPrice": "{{Quantum Slime Sell Price}}",
                    "ShopTexture": "{{ModID}}/quantum_slime_shop_texture",
                    "ShopSourceRect": {
                        "X": 0,
                        "Y": 0,
                        "Width": 32,
                        "Height": 16
                    },
                    "ShopDisplayName": "{{i18n: quantum_slime.name}}",
                    "ShopDescription": "{{i18n: quantum_slime.description |days={{Slime Days To Produce}}}}",
                    "ShopMissingBuildingDescription": "[LocalizedText Strings\\StringsFromCSFiles:Utility.cs.5926]",
                    "RequiredBuilding": "Coop",
                    "UnlockCondition": "IS_COMMUNITY_CENTER_COMPLETE",
                    "EggItemIds": [
                        "{{ModId}}.Quantum_Plort"
                    ],
                    "IncubationTime": -1,
                    "IncubatorParentSheetOffset": 1,
                    "BirthText": "{{i18n: quantum_slime.birth}}",
                    "DaysToMature": "{{Slime Days To Mature}}",
                    "CanGetPregnant": false,
                    "DaysToProduce": "{{Slime Days To Produce}}",
                    "HarvestType": 0,
                    "HarvestTool": null,
                    "ProduceItemIds": [
                        {
                            "Id": "Default",
                            "Condition": null,
                            "MinimumFriendship": 0,
                            "ItemId": "{{ModId}}.Quantum_Plort"
                        }
                    ],
                    "DeluxeProduceItemIds": [
                        {
                            "Id": "Default",
                            "Condition": null,
                            "MinimumFriendship": 0,
                            "ItemId": "{{Random: 92, 771, 16, 18, 20, 22, 399, 296, 257, 92, 309, 310, 311, 771, 398, 396, 402, 259, 420, 92, 309, 310, 311, 771, 404, 406, 408, 410, 281, 420, 92, 309, 310, 311, 771, 412, 414, 416, 418, 283, 132, 136, 138, 139, 140, 141, 142, 143, 144, 145, 153, 167, 168, 169, 170, 171, 172, 269, 424, 444, 446, 698, 699, 700, 702, 704, 706, 707, 720, 722, 767, 768, 340, (O)TulipHoney, (O)BlueJazzHoney, (O)SummarSpangleHoney, (O)PoppyHoney, (O)SunflowerHoney, (O)FairyRoseHoney, 174, 176, 180, 182, 184, 186, 426, 436, 438, 440, 442, 444, 446, 767, 787, 96, 97, 98, 99, 100, 101, 102, 103, 104, 105, 106, 107, 108, 109, 110, 111, 112, 113, 114, 115, 116, 117, 118, 119, 120, 121, 122, 123, 124, 125, 126, 127, 579, 580, 581, 582, 583, 584, 585, 586, 587, 588, 589, 881, 535, 536, 537, 749, 909, 286, 287, 288, 80, 82, 60, 62, 64, 66, 68, 70, 72, 591, 597, 376, 402, 421, 593, 421, 595, 418}}"
                        }
                    ],
                    "ProduceOnMature": false,
                    "FriendshipForFasterProduce": -1,
                    "DeluxeProduceMinimumFriendship": 200,
                    "DeluxeProduceCareDivisor": 1200.0,
                    "DeluxeProduceLuckMultiplier": 0.0,
                    "ProfessionForHappinessBoost": 2,
                    "ProfessionForQualityBoost": 2,
                    "ProfessionForFasterProduce": -1,
                    "Sound": "slime",
                    "BabySound": "slime",
                    "Texture": "{{ModID}}/quantum_slime",
                    "HarvestedTexture": null,
                    "BabyTexture": "{{ModID}}/quantum_slime",
                    "UseFlippedRightForLeft": true,
                    "SpriteWidth": 16,
                    "SpriteHeight": 16,
                    "Skins": null,
                    "ShadowWhenBabySwims": null,
                    "ShadowWhenBaby": null,
                    "ShadowWhenAdultSwims": null,
                    "ShadowWhenAdult": null,
                    "CanSwim": false,
                    "BabiesFollowAdults": true,
                    "GrassEatAmount": 2,
                    "HappinessDrain": 7,
                    "ShowInSummitCredits": true,
                    "CustomFields": null
                }
            }
        }
    ]
}