{
    "Changes": [
	
		// Baubles (https://www.nexusmods.com/stardewvalley/mods/29720)
		{
			"LogName": "Add compatibility patch to the Steel Charcoal Kiln",
			"Action": "EditData",
			"Target": "Data/Machines",
			"TargetField": [
				"(BC)nachonline.mps_SteelCharcoalKiln",
				"OutputRules"
			],
			"Entries": {
				"appleseed.BCP.CrystalizedStarJelly": {
					"Id": "appleseed.BCP.CrystalizedStarJelly",
					"Triggers": [
						{
							"RequiredItemId": "(O)appleseed.BCP.StarJelly"
						}
					],
					"OutputItem": [
						{
							"ItemId": "(O)appleseed.BCP.CrystalizedStarJelly"
						}
					],
					"MinutesUntilReady": 30
				}
			},
			"When": {
				"HasMod": "appleseed.BCP"
			}
		},
		{
			"LogName": "Add compatibility patch to the Gold Charcoal Kiln",
			"Action": "EditData",
			"Target": "Data/Machines",
			"TargetField": [
				"(BC)nachonline.mps_GoldCharcoalKiln",
				"OutputRules"
			],
			"Entries": {
				"appleseed.BCP.CrystalizedStarJelly": {
					"Id": "appleseed.BCP.CrystalizedStarJelly",
					"Triggers": [
						{
							"RequiredItemId": "(O)appleseed.BCP.StarJelly"
						}
					],
					"OutputItem": [
						{
							"ItemId": "(O)appleseed.BCP.CrystalizedStarJelly"
						}
					],
					"MinutesUntilReady": 30
				}
			},
			"When": {
				"HasMod": "appleseed.BCP"
			}
		},
		{
			"LogName": "Add compatibility patch to the Diamond Charcoal Kiln",
			"Action": "EditData",
			"Target": "Data/Machines",
			"TargetField": [
				"(BC)nachonline.mps_DiamondCharcoalKiln",
				"OutputRules"
			],
			"Entries": {
				"appleseed.BCP.CrystalizedStarJelly": {
					"Id": "appleseed.BCP.CrystalizedStarJelly",
					"Triggers": [
						{
							"RequiredItemId": "(O)appleseed.BCP.StarJelly"
						}
					],
					"OutputItem": [
						{
							"ItemId": "(O)appleseed.BCP.CrystalizedStarJelly"
						}
					],
					"MinutesUntilReady": 30
				}
			},
			"When": {
				"HasMod": "appleseed.BCP"
			}
		},
		{
			"LogName": "Add compatibility patch to the Iridium Charcoal Kiln",
			"Action": "EditData",
			"Target": "Data/Machines",
			"TargetField": [
				"(BC)nachonline.mps_IridiumCharcoalKiln",
				"OutputRules"
			],
			"Entries": {
				"appleseed.BCP.CrystalizedStarJelly": {
					"Id": "appleseed.BCP.CrystalizedStarJelly",
					"Triggers": [
						{
							"RequiredItemId": "(O)appleseed.BCP.StarJelly"
						}
					],
					"OutputItem": [
						{
							"ItemId": "(O)appleseed.BCP.CrystalizedStarJelly"
						}
					],
					"MinutesUntilReady": 30
				}
			},
			"When": {
				"HasMod": "appleseed.BCP"
			}
		},
		{
			"LogName": "Add compatibility patch to the Radioactive Charcoal Kiln",
			"Action": "EditData",
			"Target": "Data/Machines",
			"TargetField": [
				"(BC)nachonline.mps_RadioactiveCharcoalKiln",
				"OutputRules"
			],
			"Entries": {
				"appleseed.BCP.CrystalizedStarJelly": {
					"Id": "appleseed.BCP.CrystalizedStarJelly",
					"Triggers": [
						{
							"RequiredItemId": "(O)appleseed.BCP.StarJelly"
						}
					],
					"OutputItem": [
						{
							"ItemId": "(O)appleseed.BCP.CrystalizedStarJelly"
						}
					],
					"MinutesUntilReady": 30
				}
			},
			"When": {
				"HasMod": "appleseed.BCP"
			}
		},
		{
			"LogName": "Add compatibility patch to the Prismatic Charcoal Kiln",
			"Action": "EditData",
			"Target": "Data/Machines",
			"TargetField": [
				"(BC)nachonline.mps_PrismaticCharcoalKiln",
				"OutputRules"
			],
			"Entries": {
				"appleseed.BCP.CrystalizedStarJelly": {
					"Id": "appleseed.BCP.CrystalizedStarJelly",
					"Triggers": [
						{
							"RequiredItemId": "(O)appleseed.BCP.StarJelly"
						}
					],
					"OutputItem": [
						{
							"ItemId": "(O)appleseed.BCP.CrystalizedStarJelly"
						}
					],
					"MinutesUntilReady": 30
				}
			},
			"When": {
				"HasMod": "appleseed.BCP"
			}
		},
	
		// Domesticated Dust Sprites (https://www.nexusmods.com/stardewvalley/mods/23985)
		{
			"LogName": "Add compatibility patch to the Steel Charcoal Kiln",
			"Action": "EditData",
			"Target": "Data/Machines",
			"TargetField": [
				"(BC)nachonline.mps_SteelCharcoalKiln",
				"OutputRules"
			],
			"Entries": {
				"stormdrakon.DustSprites_SmallCoalChunk": {	
					"Id": "stormdrakon.DustSprites_SmallCoalChunk",
					"Triggers": [
						{
							"RequiredItemId": "(O)stormdrakon.DustSprites_SmallCoalChunk"
						}
					],
					"OutputItem": [
						{
							"ItemId": "(O)382",
							"MinStack": "{{S.C.K Driftwood to Coal Output}}"
						}
					],
					"MinutesUntilReady": 30
				},
				"stormdrakon.DustSprites_LargeCoalChunk": {	
					"Id": "stormdrakon.DustSprites_LargeCoalChunk",
					"Triggers": [
						{
							"RequiredItemId": "(O)stormdrakon.DustSprites_LargeCoalChunk"
						}
					],
					"OutputItem": [
						{
							"ItemId": "(O)382",
							"MinStack": "{{S.C.K Hardwood to Coal Output}}"
						}
					],
					"MinutesUntilReady": 30
				}
			},
			"When": {
				"HasMod": "stormdrakon.DustSprites"
			}
		},
		{
			"LogName": "Add compatibility patch to the Gold Charcoal Kiln",
			"Action": "EditData",
			"Target": "Data/Machines",
			"TargetField": [
				"(BC)nachonline.mps_GoldCharcoalKiln",
				"OutputRules"
			],
			"Entries": {
				"stormdrakon.DustSprites_SmallCoalChunk": {	
					"Id": "stormdrakon.DustSprites_SmallCoalChunk",
					"Triggers": [
						{
							"RequiredItemId": "(O)stormdrakon.DustSprites_SmallCoalChunk"
						}
					],
					"OutputItem": [
						{
							"ItemId": "(O)382",
							"MinStack": "{{G.C.K Driftwood to Coal Output}}"
						}
					],
					"MinutesUntilReady": 30
				},
				"stormdrakon.DustSprites_LargeCoalChunk": {	
					"Id": "stormdrakon.DustSprites_LargeCoalChunk",
					"Triggers": [
						{
							"RequiredItemId": "(O)stormdrakon.DustSprites_LargeCoalChunk"
						}
					],
					"OutputItem": [
						{
							"ItemId": "(O)382",
							"MinStack": "{{G.C.K Hardwood to Coal Output}}"
						}
					],
					"MinutesUntilReady": 30
				}
			},
			"When": {
				"HasMod": "stormdrakon.DustSprites"
			}
		},
		{
			"LogName": "Add compatibility patch to the Diamond Charcoal Kiln",
			"Action": "EditData",
			"Target": "Data/Machines",
			"TargetField": [
				"(BC)nachonline.mps_DiamondCharcoalKiln",
				"OutputRules"
			],
			"Entries": {
				"stormdrakon.DustSprites_SmallCoalChunk": {	
					"Id": "stormdrakon.DustSprites_SmallCoalChunk",
					"Triggers": [
						{
							"RequiredItemId": "(O)stormdrakon.DustSprites_SmallCoalChunk"
						}
					],
					"OutputItem": [
						{
							"ItemId": "(O)382",
							"MinStack": "{{D.C.K Driftwood to Coal Output}}"
						}
					],
					"MinutesUntilReady": 30
				},
				"stormdrakon.DustSprites_LargeCoalChunk": {	
					"Id": "stormdrakon.DustSprites_LargeCoalChunk",
					"Triggers": [
						{
							"RequiredItemId": "(O)stormdrakon.DustSprites_LargeCoalChunk"
						}
					],
					"OutputItem": [
						{
							"ItemId": "(O)382",
							"MinStack": "{{D.C.K Hardwood to Coal Output}}"
						}
					],
					"MinutesUntilReady": 30
				}
			},
			"When": {
				"HasMod": "stormdrakon.DustSprites"
			}
		},
		{
			"LogName": "Add compatibility patch to the Iridium Charcoal Kiln",
			"Action": "EditData",
			"Target": "Data/Machines",
			"TargetField": [
				"(BC)nachonline.mps_IridiumCharcoalKiln",
				"OutputRules"
			],
			"Entries": {
				"stormdrakon.DustSprites_SmallCoalChunk": {	
					"Id": "stormdrakon.DustSprites_SmallCoalChunk",
					"Triggers": [
						{
							"RequiredItemId": "(O)stormdrakon.DustSprites_SmallCoalChunk"
						}
					],
					"OutputItem": [
						{
							"ItemId": "(O)382",
							"MinStack": "{{I.C.K Driftwood to Coal Output}}"
						}
					],
					"MinutesUntilReady": 30
				},
				"stormdrakon.DustSprites_LargeCoalChunk": {	
					"Id": "stormdrakon.DustSprites_LargeCoalChunk",
					"Triggers": [
						{
							"RequiredItemId": "(O)stormdrakon.DustSprites_LargeCoalChunk"
						}
					],
					"OutputItem": [
						{
							"ItemId": "(O)382",
							"MinStack": "{{I.C.K Hardwood to Coal Output}}"
						}
					],
					"MinutesUntilReady": 30
				}
			},
			"When": {
				"HasMod": "stormdrakon.DustSprites"
			}
		},
		{
			"LogName": "Add compatibility patch to the Radioactive Charcoal Kiln",
			"Action": "EditData",
			"Target": "Data/Machines",
			"TargetField": [
				"(BC)nachonline.mps_RadioactiveCharcoalKiln",
				"OutputRules"
			],
			"Entries": {
				"stormdrakon.DustSprites_SmallCoalChunk": {	
					"Id": "stormdrakon.DustSprites_SmallCoalChunk",
					"Triggers": [
						{
							"RequiredItemId": "(O)stormdrakon.DustSprites_SmallCoalChunk"
						}
					],
					"OutputItem": [
						{
							"ItemId": "(O)382",
							"MinStack": "{{R.C.K Driftwood to Coal Output}}"
						}
					],
					"MinutesUntilReady": 30
				},
				"stormdrakon.DustSprites_LargeCoalChunk": {	
					"Id": "stormdrakon.DustSprites_LargeCoalChunk",
					"Triggers": [
						{
							"RequiredItemId": "(O)stormdrakon.DustSprites_LargeCoalChunk"
						}
					],
					"OutputItem": [
						{
							"ItemId": "(O)382",
							"MinStack": "{{R.C.K Hardwood to Coal Output}}"
						}
					],
					"MinutesUntilReady": 30
				}
			},
			"When": {
				"HasMod": "stormdrakon.DustSprites"
			}
		},
		{
			"LogName": "Add compatibility patch to the Prismatic Charcoal Kiln",
			"Action": "EditData",
			"Target": "Data/Machines",
			"TargetField": [
				"(BC)nachonline.mps_PrismaticCharcoalKiln",
				"OutputRules"
			],
			"Entries": {
				"stormdrakon.DustSprites_SmallCoalChunk": {	
					"Id": "stormdrakon.DustSprites_SmallCoalChunk",
					"Triggers": [
						{
							"RequiredItemId": "(O)stormdrakon.DustSprites_SmallCoalChunk"
						}
					],
					"OutputItem": [
						{
							"ItemId": "(O)382",
							"MinStack": "{{P.C.K Driftwood to Coal Output}}"
						}
					],
					"MinutesUntilReady": 30
				},
				"stormdrakon.DustSprites_LargeCoalChunk": {	
					"Id": "stormdrakon.DustSprites_LargeCoalChunk",
					"Triggers": [
						{
							"RequiredItemId": "(O)stormdrakon.DustSprites_LargeCoalChunk"
						}
					],
					"OutputItem": [
						{
							"ItemId": "(O)382",
							"MinStack": "{{P.C.K Hardwood to Coal Output}}"
						}
					],
					"MinutesUntilReady": 30
				}
			},
			"When": {
				"HasMod": "stormdrakon.DustSprites"
			}
		},
		
		// Grow Your Meat (Inspired by PPJA Fresh Meat) (https://www.nexusmods.com/stardewvalley/mods/27240)
		{
			"LogName": "Add compatibility patch to the Steel Charcoal Kiln",
			"Action": "EditData",
			"Target": "Data/Machines",
			"TargetField": [
				"(BC)nachonline.mps_SteelCharcoalKiln",
				"OutputRules"
			],
			"Entries": {
				"Wizadroid.GYM_CowMBC": {
					"Id": "Wizadroid.GYM_CowMBC",
					"Triggers": [
						{
							"RequiredItemId": "(O)Wizadroid.GYM_CowMB"
						}
					],
					"OutputItem": [
						{
							"ItemId": "(O)Wizadroid.GYM_CowMBC",
							"CopyColor": true
						}
					],
					"MinutesUntilReady": 60
				},
				"Wizadroid.GYM_CowMAC": {
					"Id": "Wizadroid.GYM_CowMAC",
					"Triggers": [
						{
							"RequiredItemId": "(O)Wizadroid.GYM_CowMA"
						}
					],
					"OutputItem": [
						{
							"ItemId": "(O)Wizadroid.GYM_CowMAC",
							"CopyColor": true
						}
					],
					"MinutesUntilReady": 60
				},
				"Wizadroid.GYM_CowMPC": {
					"Id": "Wizadroid.GYM_CowMPC",
					"Triggers": [
						{
							"RequiredItemId": "(O)Wizadroid.GYM_CowMP"
						}
					],
					"OutputItem": [
						{
							"ItemId": "(O)Wizadroid.GYM_CowMPC",
							"CopyColor": true
						}
					],
					"MinutesUntilReady": 60
				},
				"Wizadroid.GYM_SheepMBC": {
					"Id": "Wizadroid.GYM_SheepMBC",
					"Triggers": [
						{
							"RequiredItemId": "(O)Wizadroid.GYM_SheepMB"
						}
					],
					"OutputItem": [
						{
							"ItemId": "(O)Wizadroid.GYM_SheepMBC",
							"CopyColor": true
						}
					],
					"MinutesUntilReady": 60
				},
				"Wizadroid.GYM_SheepMAC": {
					"Id": "Wizadroid.GYM_SheepMAC",
					"Triggers": [
						{
							"RequiredItemId": "(O)Wizadroid.GYM_SheepMA"
						}
					],
					"OutputItem": [
						{
							"ItemId": "(O)Wizadroid.GYM_SheepMAC",
							"CopyColor": true
						}
					],
					"MinutesUntilReady": 60
				},
				"Wizadroid.GYM_SheepMPC": {
					"Id": "Wizadroid.GYM_SheepMPC",
					"Triggers": [
						{
							"RequiredItemId": "(O)Wizadroid.GYM_SheepMP"
						}
					],
					"OutputItem": [
						{
							"ItemId": "(O)Wizadroid.GYM_SheepMPC",
							"CopyColor": true
						}
					],
					"MinutesUntilReady": 60
				},
				"Wizadroid.GYM_PigMBC": {
					"Id": "Wizadroid.GYM_PigMBC",
					"Triggers": [
						{
							"RequiredItemId": "(O)Wizadroid.GYM_PigMB"
						}
					],
					"OutputItem": [
						{
							"ItemId": "(O)Wizadroid.GYM_PigMBC",
							"CopyColor": true
						}
					],
					"MinutesUntilReady": 60
				},
				"Wizadroid.GYM_PigMAC": {
					"Id": "Wizadroid.GYM_PigMAC",
					"Triggers": [
						{
							"RequiredItemId": "(O)Wizadroid.GYM_PigMA"
						}
					],
					"OutputItem": [
						{
							"ItemId": "(O)Wizadroid.GYM_PigMAC",
							"CopyColor": true
						}
					],
					"MinutesUntilReady": 60
				},
				"Wizadroid.GYM_PigMPC": {
					"Id": "Wizadroid.GYM_PigMPC",
					"Triggers": [
						{
							"RequiredItemId": "(O)Wizadroid.GYM_PigMP"
						}
					],
					"OutputItem": [
						{
							"ItemId": "(O)Wizadroid.GYM_PigMPC",
							"CopyColor": true
						}
					],
					"MinutesUntilReady": 60
				},
				"Wizadroid.GYM_ChickenMBC": {
					"Id": "Wizadroid.GYM_ChickenMBC",
					"Triggers": [
						{
							"RequiredItemId": "(O)Wizadroid.GYM_ChickenMB"
						}
					],
					"OutputItem": [
						{
							"ItemId": "(O)Wizadroid.GYM_ChickenMBC",
							"CopyColor": true
						}
					],
					"MinutesUntilReady": 60
				},
				"Wizadroid.GYM_ChickenMAC": {
					"Id": "Wizadroid.GYM_ChickenMAC",
					"Triggers": [
						{
							"RequiredItemId": "(O)Wizadroid.GYM_ChickenMA"
						}
					],
					"OutputItem": [
						{
							"ItemId": "(O)Wizadroid.GYM_ChickenMAC",
							"CopyColor": true
						}
					],
					"MinutesUntilReady": 60
				},
				"Wizadroid.GYM_ChickenMPC": {
					"Id": "Wizadroid.GYM_ChickenMPC",
					"Triggers": [
						{
							"RequiredItemId": "(O)Wizadroid.GYM_ChickenMP"
						}
					],
					"OutputItem": [
						{
							"ItemId": "(O)Wizadroid.GYM_ChickenMPC",
							"CopyColor": true
						}
					],
					"MinutesUntilReady": 60
				},
				"Wizadroid.GYM_CowMFC": {
					"Id": "Wizadroid.GYM_CowMFC",
					"Triggers": [
						{
							"RequiredItemId": "(O)Wizadroid.GYM_CowMF"
						}
					],
					"OutputItem": [
						{
							"ItemId": "(O)Wizadroid.GYM_CowMFC",
							"CopyColor": true
						}
					],
					"MinutesUntilReady": 60
				},
				"Wizadroid.GYM_SheepMFC": {
					"Id": "Wizadroid.GYM_SheepMFC",
					"Triggers": [
						{
							"RequiredItemId": "(O)Wizadroid.GYM_SheepMF"
						}
					],
					"OutputItem": [
						{
							"ItemId": "(O)Wizadroid.GYM_SheepMFC",
							"CopyColor": true
						}
					],
					"MinutesUntilReady": 60
				},
				"Wizadroid.GYM_PigMFC": {
					"Id": "Wizadroid.GYM_PigMFC",
					"Triggers": [
						{
							"RequiredItemId": "(O)Wizadroid.GYM_PigMF"
						}
					],
					"OutputItem": [
						{
							"ItemId": "(O)Wizadroid.GYM_PigMFC",
							"CopyColor": true
						}
					],
					"MinutesUntilReady": 60
				},
				"Wizadroid.GYM_ChickenMFC": {
					"Id": "Wizadroid.GYM_ChickenMFC",
					"Triggers": [
						{
							"RequiredItemId": "(O)Wizadroid.GYM_ChickenMF"
						}
					],
					"OutputItem": [
						{
							"ItemId": "(O)Wizadroid.GYM_ChickenMFC",
							"CopyColor": true
						}
					],
					"MinutesUntilReady": 60
				},
				"Wizadroid.GYM_CowMSBC": {
					"Id": "Wizadroid.GYM_CowMSBC",
					"Triggers": [
						{
							"RequiredItemId": "(O)Wizadroid.GYM_CowMSB"
						}
					],
					"OutputItem": [
						{
							"ItemId": "(O)Wizadroid.GYM_CowMSBC",
							"CopyColor": true
						}
					],
					"MinutesUntilReady": 60
				},
				"Wizadroid.GYM_SheepMSBC": {
					"Id": "Wizadroid.GYM_SheepMSBC",
					"Triggers": [
						{
							"RequiredItemId": "(O)Wizadroid.GYM_SheepMSB"
						}
					],
					"OutputItem": [
						{
							"ItemId": "(O)Wizadroid.GYM_SheepMSBC",
							"CopyColor": true
						}
					],
					"MinutesUntilReady": 60
				},
				"Wizadroid.GYM_PigMSBC": {
					"Id": "Wizadroid.GYM_PigMSBC",
					"Triggers": [
						{
							"RequiredItemId": "(O)Wizadroid.GYM_PigMSB"
						}
					],
					"OutputItem": [
						{
							"ItemId": "(O)Wizadroid.GYM_PigMSBC",
							"CopyColor": true
						}
					],
					"MinutesUntilReady": 60
				},
				"Wizadroid.GYM_ChickenMSBC": {
					"Id": "Wizadroid.GYM_ChickenMSBC",
					"Triggers": [
						{
							"RequiredItemId": "(O)Wizadroid.GYM_ChickenMSB"
						}
					],
					"OutputItem": [
						{
							"ItemId": "(O)Wizadroid.GYM_ChickenMSBC",
							"CopyColor": true
						}
					],
					"MinutesUntilReady": 60
				},
				"Wizadroid.GYM_CowMSAC": {
					"Id": "Wizadroid.GYM_CowMSAC",
					"Triggers": [
						{
							"RequiredItemId": "(O)Wizadroid.GYM_CowMSA"
						}
					],
					"OutputItem": [
						{
							"ItemId": "(O)Wizadroid.GYM_CowMSAC",
							"CopyColor": true
						}
					],
					"MinutesUntilReady": 60
				},
				"Wizadroid.GYM_SheepMSAC": {
					"Id": "Wizadroid.GYM_SheepMSAC",
					"Triggers": [
						{
							"RequiredItemId": "(O)Wizadroid.GYM_SheepMSA"
						}
					],
					"OutputItem": [
						{
							"ItemId": "(O)Wizadroid.GYM_SheepMSAC",
							"CopyColor": true
						}
					],
					"MinutesUntilReady": 60
				},
				"Wizadroid.GYM_PigMSAC": {
					"Id": "Wizadroid.GYM_PigMSAC",
					"Triggers": [
						{
							"RequiredItemId": "(O)Wizadroid.GYM_PigMSA"
						}
					],
					"OutputItem": [
						{
							"ItemId": "(O)Wizadroid.GYM_PigMSAC",
							"CopyColor": true
						}
					],
					"MinutesUntilReady": 60
				},
				"Wizadroid.GYM_ChickenMSAC": {
					"Id": "Wizadroid.GYM_ChickenMSAC",
					"Triggers": [
						{
							"RequiredItemId": "(O)Wizadroid.GYM_ChickenMSA"
						}
					],
					"OutputItem": [
						{
							"ItemId": "(O)Wizadroid.GYM_ChickenMSAC",
							"CopyColor": true
						}
					],
					"MinutesUntilReady": 60
				},
				"Wizadroid.GYM_CowMSPC": {
					"Id": "Wizadroid.GYM_CowMSPC",
					"Triggers": [
						{
							"RequiredItemId": "(O)Wizadroid.GYM_CowMSP"
						}
					],
					"OutputItem": [
						{
							"ItemId": "(O)Wizadroid.GYM_CowMSPC",
							"CopyColor": true
						}
					],
					"MinutesUntilReady": 60
				},
				"Wizadroid.GYM_SheepMSPC": {
					"Id": "Wizadroid.GYM_SheepMSPC",
					"Triggers": [
						{
							"RequiredItemId": "(O)Wizadroid.GYM_SheepMSP"
						}
					],
					"OutputItem": [
						{
							"ItemId": "(O)Wizadroid.GYM_SheepMSPC",
							"CopyColor": true
						}
					],
					"MinutesUntilReady": 60
				},
				"Wizadroid.GYM_PigMSPC": {
					"Id": "Wizadroid.GYM_PigMSPC",
					"Triggers": [
						{
							"RequiredItemId": "(O)Wizadroid.GYM_PigMSP"
						}
					],
					"OutputItem": [
						{
							"ItemId": "(O)Wizadroid.GYM_PigMSPC",
							"CopyColor": true
						}
					],
					"MinutesUntilReady": 60
				},
				"Wizadroid.GYM_ChickenMSPC": {
					"Id": "Wizadroid.GYM_ChickenMSPC",
					"Triggers": [
						{
							"RequiredItemId": "(O)Wizadroid.GYM_ChickenMSP"
						}
					],
					"OutputItem": [
						{
							"ItemId": "(O)Wizadroid.GYM_ChickenMSPC",
							"CopyColor": true
						}
					],
					"MinutesUntilReady": 60
				},
				"Wizadroid.GYM_CowMSFC": {
					"Id": "Wizadroid.GYM_CowMSFC",
					"Triggers": [
						{
							"RequiredItemId": "(O)Wizadroid.GYM_CowMSF"
						}
					],
					"OutputItem": [
						{
							"ItemId": "(O)Wizadroid.GYM_CowMSFC",
							"CopyColor": true
						}
					],
					"MinutesUntilReady": 60
				},
				"Wizadroid.GYM_SheepMSFC": {
					"Id": "Wizadroid.GYM_SheepMSFC",
					"Triggers": [
						{
							"RequiredItemId": "(O)Wizadroid.GYM_SheepMSF"
						}
					],
					"OutputItem": [
						{
							"ItemId": "(O)Wizadroid.GYM_SheepMSFC",
							"CopyColor": true
						}
					],
					"MinutesUntilReady": 60
				},
				"Wizadroid.GYM_PigMSFC": {
					"Id": "Wizadroid.GYM_PigMSFC",
					"Triggers": [
						{
							"RequiredItemId": "(O)Wizadroid.GYM_PigMSF"
						}
					],
					"OutputItem": [
						{
							"ItemId": "(O)Wizadroid.GYM_PigMSFC",
							"CopyColor": true
						}
					],
					"MinutesUntilReady": 60
				},
				"Wizadroid.GYM_ChickenMSFC": {
					"Id": "Wizadroid.GYM_ChickenMSFC",
					"Triggers": [
						{
							"RequiredItemId": "(O)Wizadroid.GYM_ChickenMSF"
						}
					],
					"OutputItem": [
						{
							"ItemId": "(O)Wizadroid.GYM_ChickenMSFC",
							"CopyColor": true
						}
					],
					"MinutesUntilReady": 60
				}
			},
			"When": {
				"HasMod": "Wizadroid.GYM"
			}
		},
		{
			"LogName": "Add compatibility patch to the Gold Charcoal Kiln",
			"Action": "EditData",
			"Target": "Data/Machines",
			"TargetField": [
				"(BC)nachonline.mps_GoldCharcoalKiln",
				"OutputRules"
			],
			"Entries": {
				"Wizadroid.GYM_CowMBC": {
					"Id": "Wizadroid.GYM_CowMBC",
					"Triggers": [
						{
							"RequiredItemId": "(O)Wizadroid.GYM_CowMB"
						}
					],
					"OutputItem": [
						{
							"ItemId": "(O)Wizadroid.GYM_CowMBC",
							"CopyColor": true
						}
					],
					"MinutesUntilReady": 60
				},
				"Wizadroid.GYM_CowMAC": {
					"Id": "Wizadroid.GYM_CowMAC",
					"Triggers": [
						{
							"RequiredItemId": "(O)Wizadroid.GYM_CowMA"
						}
					],
					"OutputItem": [
						{
							"ItemId": "(O)Wizadroid.GYM_CowMAC",
							"CopyColor": true
						}
					],
					"MinutesUntilReady": 60
				},
				"Wizadroid.GYM_CowMPC": {
					"Id": "Wizadroid.GYM_CowMPC",
					"Triggers": [
						{
							"RequiredItemId": "(O)Wizadroid.GYM_CowMP"
						}
					],
					"OutputItem": [
						{
							"ItemId": "(O)Wizadroid.GYM_CowMPC",
							"CopyColor": true
						}
					],
					"MinutesUntilReady": 60
				},
				"Wizadroid.GYM_SheepMBC": {
					"Id": "Wizadroid.GYM_SheepMBC",
					"Triggers": [
						{
							"RequiredItemId": "(O)Wizadroid.GYM_SheepMB"
						}
					],
					"OutputItem": [
						{
							"ItemId": "(O)Wizadroid.GYM_SheepMBC",
							"CopyColor": true
						}
					],
					"MinutesUntilReady": 60
				},
				"Wizadroid.GYM_SheepMAC": {
					"Id": "Wizadroid.GYM_SheepMAC",
					"Triggers": [
						{
							"RequiredItemId": "(O)Wizadroid.GYM_SheepMA"
						}
					],
					"OutputItem": [
						{
							"ItemId": "(O)Wizadroid.GYM_SheepMAC",
							"CopyColor": true
						}
					],
					"MinutesUntilReady": 60
				},
				"Wizadroid.GYM_SheepMPC": {
					"Id": "Wizadroid.GYM_SheepMPC",
					"Triggers": [
						{
							"RequiredItemId": "(O)Wizadroid.GYM_SheepMP"
						}
					],
					"OutputItem": [
						{
							"ItemId": "(O)Wizadroid.GYM_SheepMPC",
							"CopyColor": true
						}
					],
					"MinutesUntilReady": 60
				},
				"Wizadroid.GYM_PigMBC": {
					"Id": "Wizadroid.GYM_PigMBC",
					"Triggers": [
						{
							"RequiredItemId": "(O)Wizadroid.GYM_PigMB"
						}
					],
					"OutputItem": [
						{
							"ItemId": "(O)Wizadroid.GYM_PigMBC",
							"CopyColor": true
						}
					],
					"MinutesUntilReady": 60
				},
				"Wizadroid.GYM_PigMAC": {
					"Id": "Wizadroid.GYM_PigMAC",
					"Triggers": [
						{
							"RequiredItemId": "(O)Wizadroid.GYM_PigMA"
						}
					],
					"OutputItem": [
						{
							"ItemId": "(O)Wizadroid.GYM_PigMAC",
							"CopyColor": true
						}
					],
					"MinutesUntilReady": 60
				},
				"Wizadroid.GYM_PigMPC": {
					"Id": "Wizadroid.GYM_PigMPC",
					"Triggers": [
						{
							"RequiredItemId": "(O)Wizadroid.GYM_PigMP"
						}
					],
					"OutputItem": [
						{
							"ItemId": "(O)Wizadroid.GYM_PigMPC",
							"CopyColor": true
						}
					],
					"MinutesUntilReady": 60
				},
				"Wizadroid.GYM_ChickenMBC": {
					"Id": "Wizadroid.GYM_ChickenMBC",
					"Triggers": [
						{
							"RequiredItemId": "(O)Wizadroid.GYM_ChickenMB"
						}
					],
					"OutputItem": [
						{
							"ItemId": "(O)Wizadroid.GYM_ChickenMBC",
							"CopyColor": true
						}
					],
					"MinutesUntilReady": 60
				},
				"Wizadroid.GYM_ChickenMAC": {
					"Id": "Wizadroid.GYM_ChickenMAC",
					"Triggers": [
						{
							"RequiredItemId": "(O)Wizadroid.GYM_ChickenMA"
						}
					],
					"OutputItem": [
						{
							"ItemId": "(O)Wizadroid.GYM_ChickenMAC",
							"CopyColor": true
						}
					],
					"MinutesUntilReady": 60
				},
				"Wizadroid.GYM_ChickenMPC": {
					"Id": "Wizadroid.GYM_ChickenMPC",
					"Triggers": [
						{
							"RequiredItemId": "(O)Wizadroid.GYM_ChickenMP"
						}
					],
					"OutputItem": [
						{
							"ItemId": "(O)Wizadroid.GYM_ChickenMPC",
							"CopyColor": true
						}
					],
					"MinutesUntilReady": 60
				},
				"Wizadroid.GYM_CowMFC": {
					"Id": "Wizadroid.GYM_CowMFC",
					"Triggers": [
						{
							"RequiredItemId": "(O)Wizadroid.GYM_CowMF"
						}
					],
					"OutputItem": [
						{
							"ItemId": "(O)Wizadroid.GYM_CowMFC",
							"CopyColor": true
						}
					],
					"MinutesUntilReady": 60
				},
				"Wizadroid.GYM_SheepMFC": {
					"Id": "Wizadroid.GYM_SheepMFC",
					"Triggers": [
						{
							"RequiredItemId": "(O)Wizadroid.GYM_SheepMF"
						}
					],
					"OutputItem": [
						{
							"ItemId": "(O)Wizadroid.GYM_SheepMFC",
							"CopyColor": true
						}
					],
					"MinutesUntilReady": 60
				},
				"Wizadroid.GYM_PigMFC": {
					"Id": "Wizadroid.GYM_PigMFC",
					"Triggers": [
						{
							"RequiredItemId": "(O)Wizadroid.GYM_PigMF"
						}
					],
					"OutputItem": [
						{
							"ItemId": "(O)Wizadroid.GYM_PigMFC",
							"CopyColor": true
						}
					],
					"MinutesUntilReady": 60
				},
				"Wizadroid.GYM_ChickenMFC": {
					"Id": "Wizadroid.GYM_ChickenMFC",
					"Triggers": [
						{
							"RequiredItemId": "(O)Wizadroid.GYM_ChickenMF"
						}
					],
					"OutputItem": [
						{
							"ItemId": "(O)Wizadroid.GYM_ChickenMFC",
							"CopyColor": true
						}
					],
					"MinutesUntilReady": 60
				},
				"Wizadroid.GYM_CowMSBC": {
					"Id": "Wizadroid.GYM_CowMSBC",
					"Triggers": [
						{
							"RequiredItemId": "(O)Wizadroid.GYM_CowMSB"
						}
					],
					"OutputItem": [
						{
							"ItemId": "(O)Wizadroid.GYM_CowMSBC",
							"CopyColor": true
						}
					],
					"MinutesUntilReady": 60
				},
				"Wizadroid.GYM_SheepMSBC": {
					"Id": "Wizadroid.GYM_SheepMSBC",
					"Triggers": [
						{
							"RequiredItemId": "(O)Wizadroid.GYM_SheepMSB"
						}
					],
					"OutputItem": [
						{
							"ItemId": "(O)Wizadroid.GYM_SheepMSBC",
							"CopyColor": true
						}
					],
					"MinutesUntilReady": 60
				},
				"Wizadroid.GYM_PigMSBC": {
					"Id": "Wizadroid.GYM_PigMSBC",
					"Triggers": [
						{
							"RequiredItemId": "(O)Wizadroid.GYM_PigMSB"
						}
					],
					"OutputItem": [
						{
							"ItemId": "(O)Wizadroid.GYM_PigMSBC",
							"CopyColor": true
						}
					],
					"MinutesUntilReady": 60
				},
				"Wizadroid.GYM_ChickenMSBC": {
					"Id": "Wizadroid.GYM_ChickenMSBC",
					"Triggers": [
						{
							"RequiredItemId": "(O)Wizadroid.GYM_ChickenMSB"
						}
					],
					"OutputItem": [
						{
							"ItemId": "(O)Wizadroid.GYM_ChickenMSBC",
							"CopyColor": true
						}
					],
					"MinutesUntilReady": 60
				},
				"Wizadroid.GYM_CowMSAC": {
					"Id": "Wizadroid.GYM_CowMSAC",
					"Triggers": [
						{
							"RequiredItemId": "(O)Wizadroid.GYM_CowMSA"
						}
					],
					"OutputItem": [
						{
							"ItemId": "(O)Wizadroid.GYM_CowMSAC",
							"CopyColor": true
						}
					],
					"MinutesUntilReady": 60
				},
				"Wizadroid.GYM_SheepMSAC": {
					"Id": "Wizadroid.GYM_SheepMSAC",
					"Triggers": [
						{
							"RequiredItemId": "(O)Wizadroid.GYM_SheepMSA"
						}
					],
					"OutputItem": [
						{
							"ItemId": "(O)Wizadroid.GYM_SheepMSAC",
							"CopyColor": true
						}
					],
					"MinutesUntilReady": 60
				},
				"Wizadroid.GYM_PigMSAC": {
					"Id": "Wizadroid.GYM_PigMSAC",
					"Triggers": [
						{
							"RequiredItemId": "(O)Wizadroid.GYM_PigMSA"
						}
					],
					"OutputItem": [
						{
							"ItemId": "(O)Wizadroid.GYM_PigMSAC",
							"CopyColor": true
						}
					],
					"MinutesUntilReady": 60
				},
				"Wizadroid.GYM_ChickenMSAC": {
					"Id": "Wizadroid.GYM_ChickenMSAC",
					"Triggers": [
						{
							"RequiredItemId": "(O)Wizadroid.GYM_ChickenMSA"
						}
					],
					"OutputItem": [
						{
							"ItemId": "(O)Wizadroid.GYM_ChickenMSAC",
							"CopyColor": true
						}
					],
					"MinutesUntilReady": 60
				},
				"Wizadroid.GYM_CowMSPC": {
					"Id": "Wizadroid.GYM_CowMSPC",
					"Triggers": [
						{
							"RequiredItemId": "(O)Wizadroid.GYM_CowMSP"
						}
					],
					"OutputItem": [
						{
							"ItemId": "(O)Wizadroid.GYM_CowMSPC",
							"CopyColor": true
						}
					],
					"MinutesUntilReady": 60
				},
				"Wizadroid.GYM_SheepMSPC": {
					"Id": "Wizadroid.GYM_SheepMSPC",
					"Triggers": [
						{
							"RequiredItemId": "(O)Wizadroid.GYM_SheepMSP"
						}
					],
					"OutputItem": [
						{
							"ItemId": "(O)Wizadroid.GYM_SheepMSPC",
							"CopyColor": true
						}
					],
					"MinutesUntilReady": 60
				},
				"Wizadroid.GYM_PigMSPC": {
					"Id": "Wizadroid.GYM_PigMSPC",
					"Triggers": [
						{
							"RequiredItemId": "(O)Wizadroid.GYM_PigMSP"
						}
					],
					"OutputItem": [
						{
							"ItemId": "(O)Wizadroid.GYM_PigMSPC",
							"CopyColor": true
						}
					],
					"MinutesUntilReady": 60
				},
				"Wizadroid.GYM_ChickenMSPC": {
					"Id": "Wizadroid.GYM_ChickenMSPC",
					"Triggers": [
						{
							"RequiredItemId": "(O)Wizadroid.GYM_ChickenMSP"
						}
					],
					"OutputItem": [
						{
							"ItemId": "(O)Wizadroid.GYM_ChickenMSPC",
							"CopyColor": true
						}
					],
					"MinutesUntilReady": 60
				},
				"Wizadroid.GYM_CowMSFC": {
					"Id": "Wizadroid.GYM_CowMSFC",
					"Triggers": [
						{
							"RequiredItemId": "(O)Wizadroid.GYM_CowMSF"
						}
					],
					"OutputItem": [
						{
							"ItemId": "(O)Wizadroid.GYM_CowMSFC",
							"CopyColor": true
						}
					],
					"MinutesUntilReady": 60
				},
				"Wizadroid.GYM_SheepMSFC": {
					"Id": "Wizadroid.GYM_SheepMSFC",
					"Triggers": [
						{
							"RequiredItemId": "(O)Wizadroid.GYM_SheepMSF"
						}
					],
					"OutputItem": [
						{
							"ItemId": "(O)Wizadroid.GYM_SheepMSFC",
							"CopyColor": true
						}
					],
					"MinutesUntilReady": 60
				},
				"Wizadroid.GYM_PigMSFC": {
					"Id": "Wizadroid.GYM_PigMSFC",
					"Triggers": [
						{
							"RequiredItemId": "(O)Wizadroid.GYM_PigMSF"
						}
					],
					"OutputItem": [
						{
							"ItemId": "(O)Wizadroid.GYM_PigMSFC",
							"CopyColor": true
						}
					],
					"MinutesUntilReady": 60
				},
				"Wizadroid.GYM_ChickenMSFC": {
					"Id": "Wizadroid.GYM_ChickenMSFC",
					"Triggers": [
						{
							"RequiredItemId": "(O)Wizadroid.GYM_ChickenMSF"
						}
					],
					"OutputItem": [
						{
							"ItemId": "(O)Wizadroid.GYM_ChickenMSFC",
							"CopyColor": true
						}
					],
					"MinutesUntilReady": 60
				}
			},
			"When": {
				"HasMod": "Wizadroid.GYM"
			}
		},
		{
			"LogName": "Add compatibility patch to the Diamond Charcoal Kiln",
			"Action": "EditData",
			"Target": "Data/Machines",
			"TargetField": [
				"(BC)nachonline.mps_DiamondCharcoalKiln",
				"OutputRules"
			],
			"Entries": {
				"Wizadroid.GYM_CowMBC": {
					"Id": "Wizadroid.GYM_CowMBC",
					"Triggers": [
						{
							"RequiredItemId": "(O)Wizadroid.GYM_CowMB"
						}
					],
					"OutputItem": [
						{
							"ItemId": "(O)Wizadroid.GYM_CowMBC",
							"CopyColor": true
						}
					],
					"MinutesUntilReady": 60
				},
				"Wizadroid.GYM_CowMAC": {
					"Id": "Wizadroid.GYM_CowMAC",
					"Triggers": [
						{
							"RequiredItemId": "(O)Wizadroid.GYM_CowMA"
						}
					],
					"OutputItem": [
						{
							"ItemId": "(O)Wizadroid.GYM_CowMAC",
							"CopyColor": true
						}
					],
					"MinutesUntilReady": 60
				},
				"Wizadroid.GYM_CowMPC": {
					"Id": "Wizadroid.GYM_CowMPC",
					"Triggers": [
						{
							"RequiredItemId": "(O)Wizadroid.GYM_CowMP"
						}
					],
					"OutputItem": [
						{
							"ItemId": "(O)Wizadroid.GYM_CowMPC",
							"CopyColor": true
						}
					],
					"MinutesUntilReady": 60
				},
				"Wizadroid.GYM_SheepMBC": {
					"Id": "Wizadroid.GYM_SheepMBC",
					"Triggers": [
						{
							"RequiredItemId": "(O)Wizadroid.GYM_SheepMB"
						}
					],
					"OutputItem": [
						{
							"ItemId": "(O)Wizadroid.GYM_SheepMBC",
							"CopyColor": true
						}
					],
					"MinutesUntilReady": 60
				},
				"Wizadroid.GYM_SheepMAC": {
					"Id": "Wizadroid.GYM_SheepMAC",
					"Triggers": [
						{
							"RequiredItemId": "(O)Wizadroid.GYM_SheepMA"
						}
					],
					"OutputItem": [
						{
							"ItemId": "(O)Wizadroid.GYM_SheepMAC",
							"CopyColor": true
						}
					],
					"MinutesUntilReady": 60
				},
				"Wizadroid.GYM_SheepMPC": {
					"Id": "Wizadroid.GYM_SheepMPC",
					"Triggers": [
						{
							"RequiredItemId": "(O)Wizadroid.GYM_SheepMP"
						}
					],
					"OutputItem": [
						{
							"ItemId": "(O)Wizadroid.GYM_SheepMPC",
							"CopyColor": true
						}
					],
					"MinutesUntilReady": 60
				},
				"Wizadroid.GYM_PigMBC": {
					"Id": "Wizadroid.GYM_PigMBC",
					"Triggers": [
						{
							"RequiredItemId": "(O)Wizadroid.GYM_PigMB"
						}
					],
					"OutputItem": [
						{
							"ItemId": "(O)Wizadroid.GYM_PigMBC",
							"CopyColor": true
						}
					],
					"MinutesUntilReady": 60
				},
				"Wizadroid.GYM_PigMAC": {
					"Id": "Wizadroid.GYM_PigMAC",
					"Triggers": [
						{
							"RequiredItemId": "(O)Wizadroid.GYM_PigMA"
						}
					],
					"OutputItem": [
						{
							"ItemId": "(O)Wizadroid.GYM_PigMAC",
							"CopyColor": true
						}
					],
					"MinutesUntilReady": 60
				},
				"Wizadroid.GYM_PigMPC": {
					"Id": "Wizadroid.GYM_PigMPC",
					"Triggers": [
						{
							"RequiredItemId": "(O)Wizadroid.GYM_PigMP"
						}
					],
					"OutputItem": [
						{
							"ItemId": "(O)Wizadroid.GYM_PigMPC",
							"CopyColor": true
						}
					],
					"MinutesUntilReady": 60
				},
				"Wizadroid.GYM_ChickenMBC": {
					"Id": "Wizadroid.GYM_ChickenMBC",
					"Triggers": [
						{
							"RequiredItemId": "(O)Wizadroid.GYM_ChickenMB"
						}
					],
					"OutputItem": [
						{
							"ItemId": "(O)Wizadroid.GYM_ChickenMBC",
							"CopyColor": true
						}
					],
					"MinutesUntilReady": 60
				},
				"Wizadroid.GYM_ChickenMAC": {
					"Id": "Wizadroid.GYM_ChickenMAC",
					"Triggers": [
						{
							"RequiredItemId": "(O)Wizadroid.GYM_ChickenMA"
						}
					],
					"OutputItem": [
						{
							"ItemId": "(O)Wizadroid.GYM_ChickenMAC",
							"CopyColor": true
						}
					],
					"MinutesUntilReady": 60
				},
				"Wizadroid.GYM_ChickenMPC": {
					"Id": "Wizadroid.GYM_ChickenMPC",
					"Triggers": [
						{
							"RequiredItemId": "(O)Wizadroid.GYM_ChickenMP"
						}
					],
					"OutputItem": [
						{
							"ItemId": "(O)Wizadroid.GYM_ChickenMPC",
							"CopyColor": true
						}
					],
					"MinutesUntilReady": 60
				},
				"Wizadroid.GYM_CowMFC": {
					"Id": "Wizadroid.GYM_CowMFC",
					"Triggers": [
						{
							"RequiredItemId": "(O)Wizadroid.GYM_CowMF"
						}
					],
					"OutputItem": [
						{
							"ItemId": "(O)Wizadroid.GYM_CowMFC",
							"CopyColor": true
						}
					],
					"MinutesUntilReady": 60
				},
				"Wizadroid.GYM_SheepMFC": {
					"Id": "Wizadroid.GYM_SheepMFC",
					"Triggers": [
						{
							"RequiredItemId": "(O)Wizadroid.GYM_SheepMF"
						}
					],
					"OutputItem": [
						{
							"ItemId": "(O)Wizadroid.GYM_SheepMFC",
							"CopyColor": true
						}
					],
					"MinutesUntilReady": 60
				},
				"Wizadroid.GYM_PigMFC": {
					"Id": "Wizadroid.GYM_PigMFC",
					"Triggers": [
						{
							"RequiredItemId": "(O)Wizadroid.GYM_PigMF"
						}
					],
					"OutputItem": [
						{
							"ItemId": "(O)Wizadroid.GYM_PigMFC",
							"CopyColor": true
						}
					],
					"MinutesUntilReady": 60
				},
				"Wizadroid.GYM_ChickenMFC": {
					"Id": "Wizadroid.GYM_ChickenMFC",
					"Triggers": [
						{
							"RequiredItemId": "(O)Wizadroid.GYM_ChickenMF"
						}
					],
					"OutputItem": [
						{
							"ItemId": "(O)Wizadroid.GYM_ChickenMFC",
							"CopyColor": true
						}
					],
					"MinutesUntilReady": 60
				},
				"Wizadroid.GYM_CowMSBC": {
					"Id": "Wizadroid.GYM_CowMSBC",
					"Triggers": [
						{
							"RequiredItemId": "(O)Wizadroid.GYM_CowMSB"
						}
					],
					"OutputItem": [
						{
							"ItemId": "(O)Wizadroid.GYM_CowMSBC",
							"CopyColor": true
						}
					],
					"MinutesUntilReady": 60
				},
				"Wizadroid.GYM_SheepMSBC": {
					"Id": "Wizadroid.GYM_SheepMSBC",
					"Triggers": [
						{
							"RequiredItemId": "(O)Wizadroid.GYM_SheepMSB"
						}
					],
					"OutputItem": [
						{
							"ItemId": "(O)Wizadroid.GYM_SheepMSBC",
							"CopyColor": true
						}
					],
					"MinutesUntilReady": 60
				},
				"Wizadroid.GYM_PigMSBC": {
					"Id": "Wizadroid.GYM_PigMSBC",
					"Triggers": [
						{
							"RequiredItemId": "(O)Wizadroid.GYM_PigMSB"
						}
					],
					"OutputItem": [
						{
							"ItemId": "(O)Wizadroid.GYM_PigMSBC",
							"CopyColor": true
						}
					],
					"MinutesUntilReady": 60
				},
				"Wizadroid.GYM_ChickenMSBC": {
					"Id": "Wizadroid.GYM_ChickenMSBC",
					"Triggers": [
						{
							"RequiredItemId": "(O)Wizadroid.GYM_ChickenMSB"
						}
					],
					"OutputItem": [
						{
							"ItemId": "(O)Wizadroid.GYM_ChickenMSBC",
							"CopyColor": true
						}
					],
					"MinutesUntilReady": 60
				},
				"Wizadroid.GYM_CowMSAC": {
					"Id": "Wizadroid.GYM_CowMSAC",
					"Triggers": [
						{
							"RequiredItemId": "(O)Wizadroid.GYM_CowMSA"
						}
					],
					"OutputItem": [
						{
							"ItemId": "(O)Wizadroid.GYM_CowMSAC",
							"CopyColor": true
						}
					],
					"MinutesUntilReady": 60
				},
				"Wizadroid.GYM_SheepMSAC": {
					"Id": "Wizadroid.GYM_SheepMSAC",
					"Triggers": [
						{
							"RequiredItemId": "(O)Wizadroid.GYM_SheepMSA"
						}
					],
					"OutputItem": [
						{
							"ItemId": "(O)Wizadroid.GYM_SheepMSAC",
							"CopyColor": true
						}
					],
					"MinutesUntilReady": 60
				},
				"Wizadroid.GYM_PigMSAC": {
					"Id": "Wizadroid.GYM_PigMSAC",
					"Triggers": [
						{
							"RequiredItemId": "(O)Wizadroid.GYM_PigMSA"
						}
					],
					"OutputItem": [
						{
							"ItemId": "(O)Wizadroid.GYM_PigMSAC",
							"CopyColor": true
						}
					],
					"MinutesUntilReady": 60
				},
				"Wizadroid.GYM_ChickenMSAC": {
					"Id": "Wizadroid.GYM_ChickenMSAC",
					"Triggers": [
						{
							"RequiredItemId": "(O)Wizadroid.GYM_ChickenMSA"
						}
					],
					"OutputItem": [
						{
							"ItemId": "(O)Wizadroid.GYM_ChickenMSAC",
							"CopyColor": true
						}
					],
					"MinutesUntilReady": 60
				},
				"Wizadroid.GYM_CowMSPC": {
					"Id": "Wizadroid.GYM_CowMSPC",
					"Triggers": [
						{
							"RequiredItemId": "(O)Wizadroid.GYM_CowMSP"
						}
					],
					"OutputItem": [
						{
							"ItemId": "(O)Wizadroid.GYM_CowMSPC",
							"CopyColor": true
						}
					],
					"MinutesUntilReady": 60
				},
				"Wizadroid.GYM_SheepMSPC": {
					"Id": "Wizadroid.GYM_SheepMSPC",
					"Triggers": [
						{
							"RequiredItemId": "(O)Wizadroid.GYM_SheepMSP"
						}
					],
					"OutputItem": [
						{
							"ItemId": "(O)Wizadroid.GYM_SheepMSPC",
							"CopyColor": true
						}
					],
					"MinutesUntilReady": 60
				},
				"Wizadroid.GYM_PigMSPC": {
					"Id": "Wizadroid.GYM_PigMSPC",
					"Triggers": [
						{
							"RequiredItemId": "(O)Wizadroid.GYM_PigMSP"
						}
					],
					"OutputItem": [
						{
							"ItemId": "(O)Wizadroid.GYM_PigMSPC",
							"CopyColor": true
						}
					],
					"MinutesUntilReady": 60
				},
				"Wizadroid.GYM_ChickenMSPC": {
					"Id": "Wizadroid.GYM_ChickenMSPC",
					"Triggers": [
						{
							"RequiredItemId": "(O)Wizadroid.GYM_ChickenMSP"
						}
					],
					"OutputItem": [
						{
							"ItemId": "(O)Wizadroid.GYM_ChickenMSPC",
							"CopyColor": true
						}
					],
					"MinutesUntilReady": 60
				},
				"Wizadroid.GYM_CowMSFC": {
					"Id": "Wizadroid.GYM_CowMSFC",
					"Triggers": [
						{
							"RequiredItemId": "(O)Wizadroid.GYM_CowMSF"
						}
					],
					"OutputItem": [
						{
							"ItemId": "(O)Wizadroid.GYM_CowMSFC",
							"CopyColor": true
						}
					],
					"MinutesUntilReady": 60
				},
				"Wizadroid.GYM_SheepMSFC": {
					"Id": "Wizadroid.GYM_SheepMSFC",
					"Triggers": [
						{
							"RequiredItemId": "(O)Wizadroid.GYM_SheepMSF"
						}
					],
					"OutputItem": [
						{
							"ItemId": "(O)Wizadroid.GYM_SheepMSFC",
							"CopyColor": true
						}
					],
					"MinutesUntilReady": 60
				},
				"Wizadroid.GYM_PigMSFC": {
					"Id": "Wizadroid.GYM_PigMSFC",
					"Triggers": [
						{
							"RequiredItemId": "(O)Wizadroid.GYM_PigMSF"
						}
					],
					"OutputItem": [
						{
							"ItemId": "(O)Wizadroid.GYM_PigMSFC",
							"CopyColor": true
						}
					],
					"MinutesUntilReady": 60
				},
				"Wizadroid.GYM_ChickenMSFC": {
					"Id": "Wizadroid.GYM_ChickenMSFC",
					"Triggers": [
						{
							"RequiredItemId": "(O)Wizadroid.GYM_ChickenMSF"
						}
					],
					"OutputItem": [
						{
							"ItemId": "(O)Wizadroid.GYM_ChickenMSFC",
							"CopyColor": true
						}
					],
					"MinutesUntilReady": 60
				}
			},
			"When": {
				"HasMod": "Wizadroid.GYM"
			}
		},
		{
			"LogName": "Add compatibility patch to the Iridium Charcoal Kiln",
			"Action": "EditData",
			"Target": "Data/Machines",
			"TargetField": [
				"(BC)nachonline.mps_IridiumCharcoalKiln",
				"OutputRules"
			],
			"Entries": {
				"Wizadroid.GYM_CowMBC": {
					"Id": "Wizadroid.GYM_CowMBC",
					"Triggers": [
						{
							"RequiredItemId": "(O)Wizadroid.GYM_CowMB"
						}
					],
					"OutputItem": [
						{
							"ItemId": "(O)Wizadroid.GYM_CowMBC",
							"CopyColor": true
						}
					],
					"MinutesUntilReady": 60
				},
				"Wizadroid.GYM_CowMAC": {
					"Id": "Wizadroid.GYM_CowMAC",
					"Triggers": [
						{
							"RequiredItemId": "(O)Wizadroid.GYM_CowMA"
						}
					],
					"OutputItem": [
						{
							"ItemId": "(O)Wizadroid.GYM_CowMAC",
							"CopyColor": true
						}
					],
					"MinutesUntilReady": 60
				},
				"Wizadroid.GYM_CowMPC": {
					"Id": "Wizadroid.GYM_CowMPC",
					"Triggers": [
						{
							"RequiredItemId": "(O)Wizadroid.GYM_CowMP"
						}
					],
					"OutputItem": [
						{
							"ItemId": "(O)Wizadroid.GYM_CowMPC",
							"CopyColor": true
						}
					],
					"MinutesUntilReady": 60
				},
				"Wizadroid.GYM_SheepMBC": {
					"Id": "Wizadroid.GYM_SheepMBC",
					"Triggers": [
						{
							"RequiredItemId": "(O)Wizadroid.GYM_SheepMB"
						}
					],
					"OutputItem": [
						{
							"ItemId": "(O)Wizadroid.GYM_SheepMBC",
							"CopyColor": true
						}
					],
					"MinutesUntilReady": 60
				},
				"Wizadroid.GYM_SheepMAC": {
					"Id": "Wizadroid.GYM_SheepMAC",
					"Triggers": [
						{
							"RequiredItemId": "(O)Wizadroid.GYM_SheepMA"
						}
					],
					"OutputItem": [
						{
							"ItemId": "(O)Wizadroid.GYM_SheepMAC",
							"CopyColor": true
						}
					],
					"MinutesUntilReady": 60
				},
				"Wizadroid.GYM_SheepMPC": {
					"Id": "Wizadroid.GYM_SheepMPC",
					"Triggers": [
						{
							"RequiredItemId": "(O)Wizadroid.GYM_SheepMP"
						}
					],
					"OutputItem": [
						{
							"ItemId": "(O)Wizadroid.GYM_SheepMPC",
							"CopyColor": true
						}
					],
					"MinutesUntilReady": 60
				},
				"Wizadroid.GYM_PigMBC": {
					"Id": "Wizadroid.GYM_PigMBC",
					"Triggers": [
						{
							"RequiredItemId": "(O)Wizadroid.GYM_PigMB"
						}
					],
					"OutputItem": [
						{
							"ItemId": "(O)Wizadroid.GYM_PigMBC",
							"CopyColor": true
						}
					],
					"MinutesUntilReady": 60
				},
				"Wizadroid.GYM_PigMAC": {
					"Id": "Wizadroid.GYM_PigMAC",
					"Triggers": [
						{
							"RequiredItemId": "(O)Wizadroid.GYM_PigMA"
						}
					],
					"OutputItem": [
						{
							"ItemId": "(O)Wizadroid.GYM_PigMAC",
							"CopyColor": true
						}
					],
					"MinutesUntilReady": 60
				},
				"Wizadroid.GYM_PigMPC": {
					"Id": "Wizadroid.GYM_PigMPC",
					"Triggers": [
						{
							"RequiredItemId": "(O)Wizadroid.GYM_PigMP"
						}
					],
					"OutputItem": [
						{
							"ItemId": "(O)Wizadroid.GYM_PigMPC",
							"CopyColor": true
						}
					],
					"MinutesUntilReady": 60
				},
				"Wizadroid.GYM_ChickenMBC": {
					"Id": "Wizadroid.GYM_ChickenMBC",
					"Triggers": [
						{
							"RequiredItemId": "(O)Wizadroid.GYM_ChickenMB"
						}
					],
					"OutputItem": [
						{
							"ItemId": "(O)Wizadroid.GYM_ChickenMBC",
							"CopyColor": true
						}
					],
					"MinutesUntilReady": 60
				},
				"Wizadroid.GYM_ChickenMAC": {
					"Id": "Wizadroid.GYM_ChickenMAC",
					"Triggers": [
						{
							"RequiredItemId": "(O)Wizadroid.GYM_ChickenMA"
						}
					],
					"OutputItem": [
						{
							"ItemId": "(O)Wizadroid.GYM_ChickenMAC",
							"CopyColor": true
						}
					],
					"MinutesUntilReady": 60
				},
				"Wizadroid.GYM_ChickenMPC": {
					"Id": "Wizadroid.GYM_ChickenMPC",
					"Triggers": [
						{
							"RequiredItemId": "(O)Wizadroid.GYM_ChickenMP"
						}
					],
					"OutputItem": [
						{
							"ItemId": "(O)Wizadroid.GYM_ChickenMPC",
							"CopyColor": true
						}
					],
					"MinutesUntilReady": 60
				},
				"Wizadroid.GYM_CowMFC": {
					"Id": "Wizadroid.GYM_CowMFC",
					"Triggers": [
						{
							"RequiredItemId": "(O)Wizadroid.GYM_CowMF"
						}
					],
					"OutputItem": [
						{
							"ItemId": "(O)Wizadroid.GYM_CowMFC",
							"CopyColor": true
						}
					],
					"MinutesUntilReady": 60
				},
				"Wizadroid.GYM_SheepMFC": {
					"Id": "Wizadroid.GYM_SheepMFC",
					"Triggers": [
						{
							"RequiredItemId": "(O)Wizadroid.GYM_SheepMF"
						}
					],
					"OutputItem": [
						{
							"ItemId": "(O)Wizadroid.GYM_SheepMFC",
							"CopyColor": true
						}
					],
					"MinutesUntilReady": 60
				},
				"Wizadroid.GYM_PigMFC": {
					"Id": "Wizadroid.GYM_PigMFC",
					"Triggers": [
						{
							"RequiredItemId": "(O)Wizadroid.GYM_PigMF"
						}
					],
					"OutputItem": [
						{
							"ItemId": "(O)Wizadroid.GYM_PigMFC",
							"CopyColor": true
						}
					],
					"MinutesUntilReady": 60
				},
				"Wizadroid.GYM_ChickenMFC": {
					"Id": "Wizadroid.GYM_ChickenMFC",
					"Triggers": [
						{
							"RequiredItemId": "(O)Wizadroid.GYM_ChickenMF"
						}
					],
					"OutputItem": [
						{
							"ItemId": "(O)Wizadroid.GYM_ChickenMFC",
							"CopyColor": true
						}
					],
					"MinutesUntilReady": 60
				},
				"Wizadroid.GYM_CowMSBC": {
					"Id": "Wizadroid.GYM_CowMSBC",
					"Triggers": [
						{
							"RequiredItemId": "(O)Wizadroid.GYM_CowMSB"
						}
					],
					"OutputItem": [
						{
							"ItemId": "(O)Wizadroid.GYM_CowMSBC",
							"CopyColor": true
						}
					],
					"MinutesUntilReady": 60
				},
				"Wizadroid.GYM_SheepMSBC": {
					"Id": "Wizadroid.GYM_SheepMSBC",
					"Triggers": [
						{
							"RequiredItemId": "(O)Wizadroid.GYM_SheepMSB"
						}
					],
					"OutputItem": [
						{
							"ItemId": "(O)Wizadroid.GYM_SheepMSBC",
							"CopyColor": true
						}
					],
					"MinutesUntilReady": 60
				},
				"Wizadroid.GYM_PigMSBC": {
					"Id": "Wizadroid.GYM_PigMSBC",
					"Triggers": [
						{
							"RequiredItemId": "(O)Wizadroid.GYM_PigMSB"
						}
					],
					"OutputItem": [
						{
							"ItemId": "(O)Wizadroid.GYM_PigMSBC",
							"CopyColor": true
						}
					],
					"MinutesUntilReady": 60
				},
				"Wizadroid.GYM_ChickenMSBC": {
					"Id": "Wizadroid.GYM_ChickenMSBC",
					"Triggers": [
						{
							"RequiredItemId": "(O)Wizadroid.GYM_ChickenMSB"
						}
					],
					"OutputItem": [
						{
							"ItemId": "(O)Wizadroid.GYM_ChickenMSBC",
							"CopyColor": true
						}
					],
					"MinutesUntilReady": 60
				},
				"Wizadroid.GYM_CowMSAC": {
					"Id": "Wizadroid.GYM_CowMSAC",
					"Triggers": [
						{
							"RequiredItemId": "(O)Wizadroid.GYM_CowMSA"
						}
					],
					"OutputItem": [
						{
							"ItemId": "(O)Wizadroid.GYM_CowMSAC",
							"CopyColor": true
						}
					],
					"MinutesUntilReady": 60
				},
				"Wizadroid.GYM_SheepMSAC": {
					"Id": "Wizadroid.GYM_SheepMSAC",
					"Triggers": [
						{
							"RequiredItemId": "(O)Wizadroid.GYM_SheepMSA"
						}
					],
					"OutputItem": [
						{
							"ItemId": "(O)Wizadroid.GYM_SheepMSAC",
							"CopyColor": true
						}
					],
					"MinutesUntilReady": 60
				},
				"Wizadroid.GYM_PigMSAC": {
					"Id": "Wizadroid.GYM_PigMSAC",
					"Triggers": [
						{
							"RequiredItemId": "(O)Wizadroid.GYM_PigMSA"
						}
					],
					"OutputItem": [
						{
							"ItemId": "(O)Wizadroid.GYM_PigMSAC",
							"CopyColor": true
						}
					],
					"MinutesUntilReady": 60
				},
				"Wizadroid.GYM_ChickenMSAC": {
					"Id": "Wizadroid.GYM_ChickenMSAC",
					"Triggers": [
						{
							"RequiredItemId": "(O)Wizadroid.GYM_ChickenMSA"
						}
					],
					"OutputItem": [
						{
							"ItemId": "(O)Wizadroid.GYM_ChickenMSAC",
							"CopyColor": true
						}
					],
					"MinutesUntilReady": 60
				},
				"Wizadroid.GYM_CowMSPC": {
					"Id": "Wizadroid.GYM_CowMSPC",
					"Triggers": [
						{
							"RequiredItemId": "(O)Wizadroid.GYM_CowMSP"
						}
					],
					"OutputItem": [
						{
							"ItemId": "(O)Wizadroid.GYM_CowMSPC",
							"CopyColor": true
						}
					],
					"MinutesUntilReady": 60
				},
				"Wizadroid.GYM_SheepMSPC": {
					"Id": "Wizadroid.GYM_SheepMSPC",
					"Triggers": [
						{
							"RequiredItemId": "(O)Wizadroid.GYM_SheepMSP"
						}
					],
					"OutputItem": [
						{
							"ItemId": "(O)Wizadroid.GYM_SheepMSPC",
							"CopyColor": true
						}
					],
					"MinutesUntilReady": 60
				},
				"Wizadroid.GYM_PigMSPC": {
					"Id": "Wizadroid.GYM_PigMSPC",
					"Triggers": [
						{
							"RequiredItemId": "(O)Wizadroid.GYM_PigMSP"
						}
					],
					"OutputItem": [
						{
							"ItemId": "(O)Wizadroid.GYM_PigMSPC",
							"CopyColor": true
						}
					],
					"MinutesUntilReady": 60
				},
				"Wizadroid.GYM_ChickenMSPC": {
					"Id": "Wizadroid.GYM_ChickenMSPC",
					"Triggers": [
						{
							"RequiredItemId": "(O)Wizadroid.GYM_ChickenMSP"
						}
					],
					"OutputItem": [
						{
							"ItemId": "(O)Wizadroid.GYM_ChickenMSPC",
							"CopyColor": true
						}
					],
					"MinutesUntilReady": 60
				},
				"Wizadroid.GYM_CowMSFC": {
					"Id": "Wizadroid.GYM_CowMSFC",
					"Triggers": [
						{
							"RequiredItemId": "(O)Wizadroid.GYM_CowMSF"
						}
					],
					"OutputItem": [
						{
							"ItemId": "(O)Wizadroid.GYM_CowMSFC",
							"CopyColor": true
						}
					],
					"MinutesUntilReady": 60
				},
				"Wizadroid.GYM_SheepMSFC": {
					"Id": "Wizadroid.GYM_SheepMSFC",
					"Triggers": [
						{
							"RequiredItemId": "(O)Wizadroid.GYM_SheepMSF"
						}
					],
					"OutputItem": [
						{
							"ItemId": "(O)Wizadroid.GYM_SheepMSFC",
							"CopyColor": true
						}
					],
					"MinutesUntilReady": 60
				},
				"Wizadroid.GYM_PigMSFC": {
					"Id": "Wizadroid.GYM_PigMSFC",
					"Triggers": [
						{
							"RequiredItemId": "(O)Wizadroid.GYM_PigMSF"
						}
					],
					"OutputItem": [
						{
							"ItemId": "(O)Wizadroid.GYM_PigMSFC",
							"CopyColor": true
						}
					],
					"MinutesUntilReady": 60
				},
				"Wizadroid.GYM_ChickenMSFC": {
					"Id": "Wizadroid.GYM_ChickenMSFC",
					"Triggers": [
						{
							"RequiredItemId": "(O)Wizadroid.GYM_ChickenMSF"
						}
					],
					"OutputItem": [
						{
							"ItemId": "(O)Wizadroid.GYM_ChickenMSFC",
							"CopyColor": true
						}
					],
					"MinutesUntilReady": 60
				}
			},
			"When": {
				"HasMod": "Wizadroid.GYM"
			}
		},
		{
			"LogName": "Add compatibility patch to the Radioactive Charcoal Kiln",
			"Action": "EditData",
			"Target": "Data/Machines",
			"TargetField": [
				"(BC)nachonline.mps_RadioactiveCharcoalKiln",
				"OutputRules"
			],
			"Entries": {
				"Wizadroid.GYM_CowMBC": {
					"Id": "Wizadroid.GYM_CowMBC",
					"Triggers": [
						{
							"RequiredItemId": "(O)Wizadroid.GYM_CowMB"
						}
					],
					"OutputItem": [
						{
							"ItemId": "(O)Wizadroid.GYM_CowMBC",
							"CopyColor": true
						}
					],
					"MinutesUntilReady": 60
				},
				"Wizadroid.GYM_CowMAC": {
					"Id": "Wizadroid.GYM_CowMAC",
					"Triggers": [
						{
							"RequiredItemId": "(O)Wizadroid.GYM_CowMA"
						}
					],
					"OutputItem": [
						{
							"ItemId": "(O)Wizadroid.GYM_CowMAC",
							"CopyColor": true
						}
					],
					"MinutesUntilReady": 60
				},
				"Wizadroid.GYM_CowMPC": {
					"Id": "Wizadroid.GYM_CowMPC",
					"Triggers": [
						{
							"RequiredItemId": "(O)Wizadroid.GYM_CowMP"
						}
					],
					"OutputItem": [
						{
							"ItemId": "(O)Wizadroid.GYM_CowMPC",
							"CopyColor": true
						}
					],
					"MinutesUntilReady": 60
				},
				"Wizadroid.GYM_SheepMBC": {
					"Id": "Wizadroid.GYM_SheepMBC",
					"Triggers": [
						{
							"RequiredItemId": "(O)Wizadroid.GYM_SheepMB"
						}
					],
					"OutputItem": [
						{
							"ItemId": "(O)Wizadroid.GYM_SheepMBC",
							"CopyColor": true
						}
					],
					"MinutesUntilReady": 60
				},
				"Wizadroid.GYM_SheepMAC": {
					"Id": "Wizadroid.GYM_SheepMAC",
					"Triggers": [
						{
							"RequiredItemId": "(O)Wizadroid.GYM_SheepMA"
						}
					],
					"OutputItem": [
						{
							"ItemId": "(O)Wizadroid.GYM_SheepMAC",
							"CopyColor": true
						}
					],
					"MinutesUntilReady": 60
				},
				"Wizadroid.GYM_SheepMPC": {
					"Id": "Wizadroid.GYM_SheepMPC",
					"Triggers": [
						{
							"RequiredItemId": "(O)Wizadroid.GYM_SheepMP"
						}
					],
					"OutputItem": [
						{
							"ItemId": "(O)Wizadroid.GYM_SheepMPC",
							"CopyColor": true
						}
					],
					"MinutesUntilReady": 60
				},
				"Wizadroid.GYM_PigMBC": {
					"Id": "Wizadroid.GYM_PigMBC",
					"Triggers": [
						{
							"RequiredItemId": "(O)Wizadroid.GYM_PigMB"
						}
					],
					"OutputItem": [
						{
							"ItemId": "(O)Wizadroid.GYM_PigMBC",
							"CopyColor": true
						}
					],
					"MinutesUntilReady": 60
				},
				"Wizadroid.GYM_PigMAC": {
					"Id": "Wizadroid.GYM_PigMAC",
					"Triggers": [
						{
							"RequiredItemId": "(O)Wizadroid.GYM_PigMA"
						}
					],
					"OutputItem": [
						{
							"ItemId": "(O)Wizadroid.GYM_PigMAC",
							"CopyColor": true
						}
					],
					"MinutesUntilReady": 60
				},
				"Wizadroid.GYM_PigMPC": {
					"Id": "Wizadroid.GYM_PigMPC",
					"Triggers": [
						{
							"RequiredItemId": "(O)Wizadroid.GYM_PigMP"
						}
					],
					"OutputItem": [
						{
							"ItemId": "(O)Wizadroid.GYM_PigMPC",
							"CopyColor": true
						}
					],
					"MinutesUntilReady": 60
				},
				"Wizadroid.GYM_ChickenMBC": {
					"Id": "Wizadroid.GYM_ChickenMBC",
					"Triggers": [
						{
							"RequiredItemId": "(O)Wizadroid.GYM_ChickenMB"
						}
					],
					"OutputItem": [
						{
							"ItemId": "(O)Wizadroid.GYM_ChickenMBC",
							"CopyColor": true
						}
					],
					"MinutesUntilReady": 60
				},
				"Wizadroid.GYM_ChickenMAC": {
					"Id": "Wizadroid.GYM_ChickenMAC",
					"Triggers": [
						{
							"RequiredItemId": "(O)Wizadroid.GYM_ChickenMA"
						}
					],
					"OutputItem": [
						{
							"ItemId": "(O)Wizadroid.GYM_ChickenMAC",
							"CopyColor": true
						}
					],
					"MinutesUntilReady": 60
				},
				"Wizadroid.GYM_ChickenMPC": {
					"Id": "Wizadroid.GYM_ChickenMPC",
					"Triggers": [
						{
							"RequiredItemId": "(O)Wizadroid.GYM_ChickenMP"
						}
					],
					"OutputItem": [
						{
							"ItemId": "(O)Wizadroid.GYM_ChickenMPC",
							"CopyColor": true
						}
					],
					"MinutesUntilReady": 60
				},
				"Wizadroid.GYM_CowMFC": {
					"Id": "Wizadroid.GYM_CowMFC",
					"Triggers": [
						{
							"RequiredItemId": "(O)Wizadroid.GYM_CowMF"
						}
					],
					"OutputItem": [
						{
							"ItemId": "(O)Wizadroid.GYM_CowMFC",
							"CopyColor": true
						}
					],
					"MinutesUntilReady": 60
				},
				"Wizadroid.GYM_SheepMFC": {
					"Id": "Wizadroid.GYM_SheepMFC",
					"Triggers": [
						{
							"RequiredItemId": "(O)Wizadroid.GYM_SheepMF"
						}
					],
					"OutputItem": [
						{
							"ItemId": "(O)Wizadroid.GYM_SheepMFC",
							"CopyColor": true
						}
					],
					"MinutesUntilReady": 60
				},
				"Wizadroid.GYM_PigMFC": {
					"Id": "Wizadroid.GYM_PigMFC",
					"Triggers": [
						{
							"RequiredItemId": "(O)Wizadroid.GYM_PigMF"
						}
					],
					"OutputItem": [
						{
							"ItemId": "(O)Wizadroid.GYM_PigMFC",
							"CopyColor": true
						}
					],
					"MinutesUntilReady": 60
				},
				"Wizadroid.GYM_ChickenMFC": {
					"Id": "Wizadroid.GYM_ChickenMFC",
					"Triggers": [
						{
							"RequiredItemId": "(O)Wizadroid.GYM_ChickenMF"
						}
					],
					"OutputItem": [
						{
							"ItemId": "(O)Wizadroid.GYM_ChickenMFC",
							"CopyColor": true
						}
					],
					"MinutesUntilReady": 60
				},
				"Wizadroid.GYM_CowMSBC": {
					"Id": "Wizadroid.GYM_CowMSBC",
					"Triggers": [
						{
							"RequiredItemId": "(O)Wizadroid.GYM_CowMSB"
						}
					],
					"OutputItem": [
						{
							"ItemId": "(O)Wizadroid.GYM_CowMSBC",
							"CopyColor": true
						}
					],
					"MinutesUntilReady": 60
				},
				"Wizadroid.GYM_SheepMSBC": {
					"Id": "Wizadroid.GYM_SheepMSBC",
					"Triggers": [
						{
							"RequiredItemId": "(O)Wizadroid.GYM_SheepMSB"
						}
					],
					"OutputItem": [
						{
							"ItemId": "(O)Wizadroid.GYM_SheepMSBC",
							"CopyColor": true
						}
					],
					"MinutesUntilReady": 60
				},
				"Wizadroid.GYM_PigMSBC": {
					"Id": "Wizadroid.GYM_PigMSBC",
					"Triggers": [
						{
							"RequiredItemId": "(O)Wizadroid.GYM_PigMSB"
						}
					],
					"OutputItem": [
						{
							"ItemId": "(O)Wizadroid.GYM_PigMSBC",
							"CopyColor": true
						}
					],
					"MinutesUntilReady": 60
				},
				"Wizadroid.GYM_ChickenMSBC": {
					"Id": "Wizadroid.GYM_ChickenMSBC",
					"Triggers": [
						{
							"RequiredItemId": "(O)Wizadroid.GYM_ChickenMSB"
						}
					],
					"OutputItem": [
						{
							"ItemId": "(O)Wizadroid.GYM_ChickenMSBC",
							"CopyColor": true
						}
					],
					"MinutesUntilReady": 60
				},
				"Wizadroid.GYM_CowMSAC": {
					"Id": "Wizadroid.GYM_CowMSAC",
					"Triggers": [
						{
							"RequiredItemId": "(O)Wizadroid.GYM_CowMSA"
						}
					],
					"OutputItem": [
						{
							"ItemId": "(O)Wizadroid.GYM_CowMSAC",
							"CopyColor": true
						}
					],
					"MinutesUntilReady": 60
				},
				"Wizadroid.GYM_SheepMSAC": {
					"Id": "Wizadroid.GYM_SheepMSAC",
					"Triggers": [
						{
							"RequiredItemId": "(O)Wizadroid.GYM_SheepMSA"
						}
					],
					"OutputItem": [
						{
							"ItemId": "(O)Wizadroid.GYM_SheepMSAC",
							"CopyColor": true
						}
					],
					"MinutesUntilReady": 60
				},
				"Wizadroid.GYM_PigMSAC": {
					"Id": "Wizadroid.GYM_PigMSAC",
					"Triggers": [
						{
							"RequiredItemId": "(O)Wizadroid.GYM_PigMSA"
						}
					],
					"OutputItem": [
						{
							"ItemId": "(O)Wizadroid.GYM_PigMSAC",
							"CopyColor": true
						}
					],
					"MinutesUntilReady": 60
				},
				"Wizadroid.GYM_ChickenMSAC": {
					"Id": "Wizadroid.GYM_ChickenMSAC",
					"Triggers": [
						{
							"RequiredItemId": "(O)Wizadroid.GYM_ChickenMSA"
						}
					],
					"OutputItem": [
						{
							"ItemId": "(O)Wizadroid.GYM_ChickenMSAC",
							"CopyColor": true
						}
					],
					"MinutesUntilReady": 60
				},
				"Wizadroid.GYM_CowMSPC": {
					"Id": "Wizadroid.GYM_CowMSPC",
					"Triggers": [
						{
							"RequiredItemId": "(O)Wizadroid.GYM_CowMSP"
						}
					],
					"OutputItem": [
						{
							"ItemId": "(O)Wizadroid.GYM_CowMSPC",
							"CopyColor": true
						}
					],
					"MinutesUntilReady": 60
				},
				"Wizadroid.GYM_SheepMSPC": {
					"Id": "Wizadroid.GYM_SheepMSPC",
					"Triggers": [
						{
							"RequiredItemId": "(O)Wizadroid.GYM_SheepMSP"
						}
					],
					"OutputItem": [
						{
							"ItemId": "(O)Wizadroid.GYM_SheepMSPC",
							"CopyColor": true
						}
					],
					"MinutesUntilReady": 60
				},
				"Wizadroid.GYM_PigMSPC": {
					"Id": "Wizadroid.GYM_PigMSPC",
					"Triggers": [
						{
							"RequiredItemId": "(O)Wizadroid.GYM_PigMSP"
						}
					],
					"OutputItem": [
						{
							"ItemId": "(O)Wizadroid.GYM_PigMSPC",
							"CopyColor": true
						}
					],
					"MinutesUntilReady": 60
				},
				"Wizadroid.GYM_ChickenMSPC": {
					"Id": "Wizadroid.GYM_ChickenMSPC",
					"Triggers": [
						{
							"RequiredItemId": "(O)Wizadroid.GYM_ChickenMSP"
						}
					],
					"OutputItem": [
						{
							"ItemId": "(O)Wizadroid.GYM_ChickenMSPC",
							"CopyColor": true
						}
					],
					"MinutesUntilReady": 60
				},
				"Wizadroid.GYM_CowMSFC": {
					"Id": "Wizadroid.GYM_CowMSFC",
					"Triggers": [
						{
							"RequiredItemId": "(O)Wizadroid.GYM_CowMSF"
						}
					],
					"OutputItem": [
						{
							"ItemId": "(O)Wizadroid.GYM_CowMSFC",
							"CopyColor": true
						}
					],
					"MinutesUntilReady": 60
				},
				"Wizadroid.GYM_SheepMSFC": {
					"Id": "Wizadroid.GYM_SheepMSFC",
					"Triggers": [
						{
							"RequiredItemId": "(O)Wizadroid.GYM_SheepMSF"
						}
					],
					"OutputItem": [
						{
							"ItemId": "(O)Wizadroid.GYM_SheepMSFC",
							"CopyColor": true
						}
					],
					"MinutesUntilReady": 60
				},
				"Wizadroid.GYM_PigMSFC": {
					"Id": "Wizadroid.GYM_PigMSFC",
					"Triggers": [
						{
							"RequiredItemId": "(O)Wizadroid.GYM_PigMSF"
						}
					],
					"OutputItem": [
						{
							"ItemId": "(O)Wizadroid.GYM_PigMSFC",
							"CopyColor": true
						}
					],
					"MinutesUntilReady": 60
				},
				"Wizadroid.GYM_ChickenMSFC": {
					"Id": "Wizadroid.GYM_ChickenMSFC",
					"Triggers": [
						{
							"RequiredItemId": "(O)Wizadroid.GYM_ChickenMSF"
						}
					],
					"OutputItem": [
						{
							"ItemId": "(O)Wizadroid.GYM_ChickenMSFC",
							"CopyColor": true
						}
					],
					"MinutesUntilReady": 60
				}
			},
			"When": {
				"HasMod": "Wizadroid.GYM"
			}
		},
		{
			"LogName": "Add compatibility patch to the Prismatic Charcoal Kiln",
			"Action": "EditData",
			"Target": "Data/Machines",
			"TargetField": [
				"(BC)nachonline.mps_PrismaticCharcoalKiln",
				"OutputRules"
			],
			"Entries": {
				"Wizadroid.GYM_CowMBC": {
					"Id": "Wizadroid.GYM_CowMBC",
					"Triggers": [
						{
							"RequiredItemId": "(O)Wizadroid.GYM_CowMB"
						}
					],
					"OutputItem": [
						{
							"ItemId": "(O)Wizadroid.GYM_CowMBC",
							"CopyColor": true
						}
					],
					"MinutesUntilReady": 60
				},
				"Wizadroid.GYM_CowMAC": {
					"Id": "Wizadroid.GYM_CowMAC",
					"Triggers": [
						{
							"RequiredItemId": "(O)Wizadroid.GYM_CowMA"
						}
					],
					"OutputItem": [
						{
							"ItemId": "(O)Wizadroid.GYM_CowMAC",
							"CopyColor": true
						}
					],
					"MinutesUntilReady": 60
				},
				"Wizadroid.GYM_CowMPC": {
					"Id": "Wizadroid.GYM_CowMPC",
					"Triggers": [
						{
							"RequiredItemId": "(O)Wizadroid.GYM_CowMP"
						}
					],
					"OutputItem": [
						{
							"ItemId": "(O)Wizadroid.GYM_CowMPC",
							"CopyColor": true
						}
					],
					"MinutesUntilReady": 60
				},
				"Wizadroid.GYM_SheepMBC": {
					"Id": "Wizadroid.GYM_SheepMBC",
					"Triggers": [
						{
							"RequiredItemId": "(O)Wizadroid.GYM_SheepMB"
						}
					],
					"OutputItem": [
						{
							"ItemId": "(O)Wizadroid.GYM_SheepMBC",
							"CopyColor": true
						}
					],
					"MinutesUntilReady": 60
				},
				"Wizadroid.GYM_SheepMAC": {
					"Id": "Wizadroid.GYM_SheepMAC",
					"Triggers": [
						{
							"RequiredItemId": "(O)Wizadroid.GYM_SheepMA"
						}
					],
					"OutputItem": [
						{
							"ItemId": "(O)Wizadroid.GYM_SheepMAC",
							"CopyColor": true
						}
					],
					"MinutesUntilReady": 60
				},
				"Wizadroid.GYM_SheepMPC": {
					"Id": "Wizadroid.GYM_SheepMPC",
					"Triggers": [
						{
							"RequiredItemId": "(O)Wizadroid.GYM_SheepMP"
						}
					],
					"OutputItem": [
						{
							"ItemId": "(O)Wizadroid.GYM_SheepMPC",
							"CopyColor": true
						}
					],
					"MinutesUntilReady": 60
				},
				"Wizadroid.GYM_PigMBC": {
					"Id": "Wizadroid.GYM_PigMBC",
					"Triggers": [
						{
							"RequiredItemId": "(O)Wizadroid.GYM_PigMB"
						}
					],
					"OutputItem": [
						{
							"ItemId": "(O)Wizadroid.GYM_PigMBC",
							"CopyColor": true
						}
					],
					"MinutesUntilReady": 60
				},
				"Wizadroid.GYM_PigMAC": {
					"Id": "Wizadroid.GYM_PigMAC",
					"Triggers": [
						{
							"RequiredItemId": "(O)Wizadroid.GYM_PigMA"
						}
					],
					"OutputItem": [
						{
							"ItemId": "(O)Wizadroid.GYM_PigMAC",
							"CopyColor": true
						}
					],
					"MinutesUntilReady": 60
				},
				"Wizadroid.GYM_PigMPC": {
					"Id": "Wizadroid.GYM_PigMPC",
					"Triggers": [
						{
							"RequiredItemId": "(O)Wizadroid.GYM_PigMP"
						}
					],
					"OutputItem": [
						{
							"ItemId": "(O)Wizadroid.GYM_PigMPC",
							"CopyColor": true
						}
					],
					"MinutesUntilReady": 60
				},
				"Wizadroid.GYM_ChickenMBC": {
					"Id": "Wizadroid.GYM_ChickenMBC",
					"Triggers": [
						{
							"RequiredItemId": "(O)Wizadroid.GYM_ChickenMB"
						}
					],
					"OutputItem": [
						{
							"ItemId": "(O)Wizadroid.GYM_ChickenMBC",
							"CopyColor": true
						}
					],
					"MinutesUntilReady": 60
				},
				"Wizadroid.GYM_ChickenMAC": {
					"Id": "Wizadroid.GYM_ChickenMAC",
					"Triggers": [
						{
							"RequiredItemId": "(O)Wizadroid.GYM_ChickenMA"
						}
					],
					"OutputItem": [
						{
							"ItemId": "(O)Wizadroid.GYM_ChickenMAC",
							"CopyColor": true
						}
					],
					"MinutesUntilReady": 60
				},
				"Wizadroid.GYM_ChickenMPC": {
					"Id": "Wizadroid.GYM_ChickenMPC",
					"Triggers": [
						{
							"RequiredItemId": "(O)Wizadroid.GYM_ChickenMP"
						}
					],
					"OutputItem": [
						{
							"ItemId": "(O)Wizadroid.GYM_ChickenMPC",
							"CopyColor": true
						}
					],
					"MinutesUntilReady": 60
				},
				"Wizadroid.GYM_CowMFC": {
					"Id": "Wizadroid.GYM_CowMFC",
					"Triggers": [
						{
							"RequiredItemId": "(O)Wizadroid.GYM_CowMF"
						}
					],
					"OutputItem": [
						{
							"ItemId": "(O)Wizadroid.GYM_CowMFC",
							"CopyColor": true
						}
					],
					"MinutesUntilReady": 60
				},
				"Wizadroid.GYM_SheepMFC": {
					"Id": "Wizadroid.GYM_SheepMFC",
					"Triggers": [
						{
							"RequiredItemId": "(O)Wizadroid.GYM_SheepMF"
						}
					],
					"OutputItem": [
						{
							"ItemId": "(O)Wizadroid.GYM_SheepMFC",
							"CopyColor": true
						}
					],
					"MinutesUntilReady": 60
				},
				"Wizadroid.GYM_PigMFC": {
					"Id": "Wizadroid.GYM_PigMFC",
					"Triggers": [
						{
							"RequiredItemId": "(O)Wizadroid.GYM_PigMF"
						}
					],
					"OutputItem": [
						{
							"ItemId": "(O)Wizadroid.GYM_PigMFC",
							"CopyColor": true
						}
					],
					"MinutesUntilReady": 60
				},
				"Wizadroid.GYM_ChickenMFC": {
					"Id": "Wizadroid.GYM_ChickenMFC",
					"Triggers": [
						{
							"RequiredItemId": "(O)Wizadroid.GYM_ChickenMF"
						}
					],
					"OutputItem": [
						{
							"ItemId": "(O)Wizadroid.GYM_ChickenMFC",
							"CopyColor": true
						}
					],
					"MinutesUntilReady": 60
				},
				"Wizadroid.GYM_CowMSBC": {
					"Id": "Wizadroid.GYM_CowMSBC",
					"Triggers": [
						{
							"RequiredItemId": "(O)Wizadroid.GYM_CowMSB"
						}
					],
					"OutputItem": [
						{
							"ItemId": "(O)Wizadroid.GYM_CowMSBC",
							"CopyColor": true
						}
					],
					"MinutesUntilReady": 60
				},
				"Wizadroid.GYM_SheepMSBC": {
					"Id": "Wizadroid.GYM_SheepMSBC",
					"Triggers": [
						{
							"RequiredItemId": "(O)Wizadroid.GYM_SheepMSB"
						}
					],
					"OutputItem": [
						{
							"ItemId": "(O)Wizadroid.GYM_SheepMSBC",
							"CopyColor": true
						}
					],
					"MinutesUntilReady": 60
				},
				"Wizadroid.GYM_PigMSBC": {
					"Id": "Wizadroid.GYM_PigMSBC",
					"Triggers": [
						{
							"RequiredItemId": "(O)Wizadroid.GYM_PigMSB"
						}
					],
					"OutputItem": [
						{
							"ItemId": "(O)Wizadroid.GYM_PigMSBC",
							"CopyColor": true
						}
					],
					"MinutesUntilReady": 60
				},
				"Wizadroid.GYM_ChickenMSBC": {
					"Id": "Wizadroid.GYM_ChickenMSBC",
					"Triggers": [
						{
							"RequiredItemId": "(O)Wizadroid.GYM_ChickenMSB"
						}
					],
					"OutputItem": [
						{
							"ItemId": "(O)Wizadroid.GYM_ChickenMSBC",
							"CopyColor": true
						}
					],
					"MinutesUntilReady": 60
				},
				"Wizadroid.GYM_CowMSAC": {
					"Id": "Wizadroid.GYM_CowMSAC",
					"Triggers": [
						{
							"RequiredItemId": "(O)Wizadroid.GYM_CowMSA"
						}
					],
					"OutputItem": [
						{
							"ItemId": "(O)Wizadroid.GYM_CowMSAC",
							"CopyColor": true
						}
					],
					"MinutesUntilReady": 60
				},
				"Wizadroid.GYM_SheepMSAC": {
					"Id": "Wizadroid.GYM_SheepMSAC",
					"Triggers": [
						{
							"RequiredItemId": "(O)Wizadroid.GYM_SheepMSA"
						}
					],
					"OutputItem": [
						{
							"ItemId": "(O)Wizadroid.GYM_SheepMSAC",
							"CopyColor": true
						}
					],
					"MinutesUntilReady": 60
				},
				"Wizadroid.GYM_PigMSAC": {
					"Id": "Wizadroid.GYM_PigMSAC",
					"Triggers": [
						{
							"RequiredItemId": "(O)Wizadroid.GYM_PigMSA"
						}
					],
					"OutputItem": [
						{
							"ItemId": "(O)Wizadroid.GYM_PigMSAC",
							"CopyColor": true
						}
					],
					"MinutesUntilReady": 60
				},
				"Wizadroid.GYM_ChickenMSAC": {
					"Id": "Wizadroid.GYM_ChickenMSAC",
					"Triggers": [
						{
							"RequiredItemId": "(O)Wizadroid.GYM_ChickenMSA"
						}
					],
					"OutputItem": [
						{
							"ItemId": "(O)Wizadroid.GYM_ChickenMSAC",
							"CopyColor": true
						}
					],
					"MinutesUntilReady": 60
				},
				"Wizadroid.GYM_CowMSPC": {
					"Id": "Wizadroid.GYM_CowMSPC",
					"Triggers": [
						{
							"RequiredItemId": "(O)Wizadroid.GYM_CowMSP"
						}
					],
					"OutputItem": [
						{
							"ItemId": "(O)Wizadroid.GYM_CowMSPC",
							"CopyColor": true
						}
					],
					"MinutesUntilReady": 60
				},
				"Wizadroid.GYM_SheepMSPC": {
					"Id": "Wizadroid.GYM_SheepMSPC",
					"Triggers": [
						{
							"RequiredItemId": "(O)Wizadroid.GYM_SheepMSP"
						}
					],
					"OutputItem": [
						{
							"ItemId": "(O)Wizadroid.GYM_SheepMSPC",
							"CopyColor": true
						}
					],
					"MinutesUntilReady": 60
				},
				"Wizadroid.GYM_PigMSPC": {
					"Id": "Wizadroid.GYM_PigMSPC",
					"Triggers": [
						{
							"RequiredItemId": "(O)Wizadroid.GYM_PigMSP"
						}
					],
					"OutputItem": [
						{
							"ItemId": "(O)Wizadroid.GYM_PigMSPC",
							"CopyColor": true
						}
					],
					"MinutesUntilReady": 60
				},
				"Wizadroid.GYM_ChickenMSPC": {
					"Id": "Wizadroid.GYM_ChickenMSPC",
					"Triggers": [
						{
							"RequiredItemId": "(O)Wizadroid.GYM_ChickenMSP"
						}
					],
					"OutputItem": [
						{
							"ItemId": "(O)Wizadroid.GYM_ChickenMSPC",
							"CopyColor": true
						}
					],
					"MinutesUntilReady": 60
				},
				"Wizadroid.GYM_CowMSFC": {
					"Id": "Wizadroid.GYM_CowMSFC",
					"Triggers": [
						{
							"RequiredItemId": "(O)Wizadroid.GYM_CowMSF"
						}
					],
					"OutputItem": [
						{
							"ItemId": "(O)Wizadroid.GYM_CowMSFC",
							"CopyColor": true
						}
					],
					"MinutesUntilReady": 60
				},
				"Wizadroid.GYM_SheepMSFC": {
					"Id": "Wizadroid.GYM_SheepMSFC",
					"Triggers": [
						{
							"RequiredItemId": "(O)Wizadroid.GYM_SheepMSF"
						}
					],
					"OutputItem": [
						{
							"ItemId": "(O)Wizadroid.GYM_SheepMSFC",
							"CopyColor": true
						}
					],
					"MinutesUntilReady": 60
				},
				"Wizadroid.GYM_PigMSFC": {
					"Id": "Wizadroid.GYM_PigMSFC",
					"Triggers": [
						{
							"RequiredItemId": "(O)Wizadroid.GYM_PigMSF"
						}
					],
					"OutputItem": [
						{
							"ItemId": "(O)Wizadroid.GYM_PigMSFC",
							"CopyColor": true
						}
					],
					"MinutesUntilReady": 60
				},
				"Wizadroid.GYM_ChickenMSFC": {
					"Id": "Wizadroid.GYM_ChickenMSFC",
					"Triggers": [
						{
							"RequiredItemId": "(O)Wizadroid.GYM_ChickenMSF"
						}
					],
					"OutputItem": [
						{
							"ItemId": "(O)Wizadroid.GYM_ChickenMSFC",
							"CopyColor": true
						}
					],
					"MinutesUntilReady": 60
				}
			},
			"When": {
				"HasMod": "Wizadroid.GYM"
			}
		},
		
		// Immersive Manure (https://www.nexusmods.com/stardewvalley/mods/27432)
		{
			"LogName": "Add compatibility patch to the Steel Charcoal Kiln",
			"Action": "EditData",
			"Target": "Data/Machines",
			"TargetField": [
				"(BC)nachonline.mps_SteelCharcoalKiln",
				"OutputRules"
			],
			"Entries": {
				"selph.ImmersiveManure_ManureToCoal": {
					"Id": "selph.ImmersiveManure_ManureToCoal",
					"Triggers": [
						{
							"RequiredItemId": "(O)selph.ImmersiveManure.PoultryManure"
						},
						{
							"RequiredItemId": "(O)selph.ImmersiveManure.LivestockManure"
						},
					],
					"OutputItem": [
						{
							"ItemId": "(O)382",
							"StackModifiers": [
								{
									"Id": "DoubleQuality",
									"Condition": "ANY \"ITEM_QUALITY Input 1 1, RANDOM 0.25\" \"ITEM_QUALITY Input 2 2, RANDOM 0.5\" \"ITEM_QUALITY Input 4 4, RANDOM 1\"",
									"Modification": "Add",
									"Amount": 1
								}
							],
							"StackModifierMode": "Stack"
						}
					],
					"MinutesUntilReady": 30
				}
			},
			"When": {
				"HasMod": "selph.ImmersiveManure"
			}
		},
		{
			"LogName": "Add compatibility patch to the Gold Charcoal Kiln",
			"Action": "EditData",
			"Target": "Data/Machines",
			"TargetField": [
				"(BC)nachonline.mps_GoldCharcoalKiln",
				"OutputRules"
			],
			"Entries": {
				"selph.ImmersiveManure_ManureToCoal": {
					"Id": "selph.ImmersiveManure_ManureToCoal",
					"Triggers": [
						{
							"RequiredItemId": "(O)selph.ImmersiveManure.PoultryManure"
						},
						{
							"RequiredItemId": "(O)selph.ImmersiveManure.LivestockManure"
						},
					],
					"OutputItem": [
						{
							"ItemId": "(O)382",
							"StackModifiers": [
								{
									"Id": "DoubleQuality",
									"Condition": "ANY \"ITEM_QUALITY Input 1 1, RANDOM 0.25\" \"ITEM_QUALITY Input 2 2, RANDOM 0.5\" \"ITEM_QUALITY Input 4 4, RANDOM 1\"",
									"Modification": "Add",
									"Amount": 1
								}
							],
							"StackModifierMode": "Stack"
						}
					],
					"MinutesUntilReady": 30
				}
			},
			"When": {
				"HasMod": "selph.ImmersiveManure"
			}
		},
		{
			"LogName": "Add compatibility patch to the Diamond Charcoal Kiln",
			"Action": "EditData",
			"Target": "Data/Machines",
			"TargetField": [
				"(BC)nachonline.mps_DiamondCharcoalKiln",
				"OutputRules"
			],
			"Entries": {
				"selph.ImmersiveManure_ManureToCoal": {
					"Id": "selph.ImmersiveManure_ManureToCoal",
					"Triggers": [
						{
							"RequiredItemId": "(O)selph.ImmersiveManure.PoultryManure"
						},
						{
							"RequiredItemId": "(O)selph.ImmersiveManure.LivestockManure"
						},
					],
					"OutputItem": [
						{
							"ItemId": "(O)382",
							"StackModifiers": [
								{
									"Id": "DoubleQuality",
									"Condition": "ANY \"ITEM_QUALITY Input 1 1, RANDOM 0.25\" \"ITEM_QUALITY Input 2 2, RANDOM 0.5\" \"ITEM_QUALITY Input 4 4, RANDOM 1\"",
									"Modification": "Add",
									"Amount": 1
								}
							],
							"StackModifierMode": "Stack"
						}
					],
					"MinutesUntilReady": 30
				}
			},
			"When": {
				"HasMod": "selph.ImmersiveManure"
			}
		},
		{
			"LogName": "Add compatibility patch to the Iridium Charcoal Kiln",
			"Action": "EditData",
			"Target": "Data/Machines",
			"TargetField": [
				"(BC)nachonline.mps_IridiumCharcoalKiln",
				"OutputRules"
			],
			"Entries": {
				"selph.ImmersiveManure_ManureToCoal": {
					"Id": "selph.ImmersiveManure_ManureToCoal",
					"Triggers": [
						{
							"RequiredItemId": "(O)selph.ImmersiveManure.PoultryManure"
						},
						{
							"RequiredItemId": "(O)selph.ImmersiveManure.LivestockManure"
						},
					],
					"OutputItem": [
						{
							"ItemId": "(O)382",
							"StackModifiers": [
								{
									"Id": "DoubleQuality",
									"Condition": "ANY \"ITEM_QUALITY Input 1 1, RANDOM 0.25\" \"ITEM_QUALITY Input 2 2, RANDOM 0.5\" \"ITEM_QUALITY Input 4 4, RANDOM 1\"",
									"Modification": "Add",
									"Amount": 1
								}
							],
							"StackModifierMode": "Stack"
						}
					],
					"MinutesUntilReady": 30
				}
			},
			"When": {
				"HasMod": "selph.ImmersiveManure"
			}
		},
		{
			"LogName": "Add compatibility patch to the Radioactive Charcoal Kiln",
			"Action": "EditData",
			"Target": "Data/Machines",
			"TargetField": [
				"(BC)nachonline.mps_RadioactiveCharcoalKiln",
				"OutputRules"
			],
			"Entries": {
				"selph.ImmersiveManure_ManureToCoal": {
					"Id": "selph.ImmersiveManure_ManureToCoal",
					"Triggers": [
						{
							"RequiredItemId": "(O)selph.ImmersiveManure.PoultryManure"
						},
						{
							"RequiredItemId": "(O)selph.ImmersiveManure.LivestockManure"
						},
					],
					"OutputItem": [
						{
							"ItemId": "(O)382",
							"StackModifiers": [
								{
									"Id": "DoubleQuality",
									"Condition": "ANY \"ITEM_QUALITY Input 1 1, RANDOM 0.25\" \"ITEM_QUALITY Input 2 2, RANDOM 0.5\" \"ITEM_QUALITY Input 4 4, RANDOM 1\"",
									"Modification": "Add",
									"Amount": 1
								}
							],
							"StackModifierMode": "Stack"
						}
					],
					"MinutesUntilReady": 30
				}
			},
			"When": {
				"HasMod": "selph.ImmersiveManure"
			}
		},
		{
			"LogName": "Add compatibility patch to the Prismatic Charcoal Kiln",
			"Action": "EditData",
			"Target": "Data/Machines",
			"TargetField": [
				"(BC)nachonline.mps_PrismaticCharcoalKiln",
				"OutputRules"
			],
			"Entries": {
				"selph.ImmersiveManure_ManureToCoal": {
					"Id": "selph.ImmersiveManure_ManureToCoal",
					"Triggers": [
						{
							"RequiredItemId": "(O)selph.ImmersiveManure.PoultryManure"
						},
						{
							"RequiredItemId": "(O)selph.ImmersiveManure.LivestockManure"
						},
					],
					"OutputItem": [
						{
							"ItemId": "(O)382",
							"StackModifiers": [
								{
									"Id": "DoubleQuality",
									"Condition": "ANY \"ITEM_QUALITY Input 1 1, RANDOM 0.25\" \"ITEM_QUALITY Input 2 2, RANDOM 0.5\" \"ITEM_QUALITY Input 4 4, RANDOM 1\"",
									"Modification": "Add",
									"Amount": 1
								}
							],
							"StackModifierMode": "Stack"
						}
					],
					"MinutesUntilReady": 30
				}
			},
			"When": {
				"HasMod": "selph.ImmersiveManure"
			}
		},
		
		// Lumisteria Visit Mount Vapius (https://www.nexusmods.com/stardewvalley/mods/9600)
		{
			"LogName": "Add compatibility patch to the Steel Charcoal Kiln",
			"Action": "EditData",
			"Target": "Data/Machines",
			"TargetField": [
				"(BC)nachonline.mps_SteelCharcoalKiln",
				"OutputRules"
			],
			"Entries": {
				"Lumisteria.MtVapius_CharcoalKilnRules": {
					"Id": "Lumisteria.MtVapius_CharcoalKilnRules",
					"Triggers": [
						{
							"RequiredItemId": "(O)Lumisteria.MtVapius_NightMiscanthus"
						}
					],
					"OutputItem": [
						{
							"ItemId": "(O)382",
							"MinStack": "{{S.C.K Driftwood to Coal Output}}",
							"StackModifiers": [
								{
									"Id": "DoubleSilverQuality",
									"Condition": "ITEM_QUALITY Input 1, !ITEM_QUALITY Input 2, RANDOM 0.1",
									"Modification": "Multiply",
									"Amount": 2.0
								},
								{
									"Id": "DoubleGoldQuality",
									"Condition": "ITEM_QUALITY Input 2, !ITEM_QUALITY Input 3, RANDOM 0.25",
									"Modification": "Multiply",
									"Amount": 2.0
								},
								{
									"Id": "DoubleIridiumQuality",
									"Condition": "ITEM_QUALITY Input 4, !ITEM_QUALITY Input 5, RANDOM 0.5",
									"Modification": "Multiply",
									"Amount": 2.0
								}
							],
							"StackModifierMode": "Stack"
						}
					],
					"MinutesUntilReady": 240
				}
			},
			"When": {
				"HasMod": "Lumisteria.MtVapius"
			}
		},
		{
			"LogName": "Add compatibility patch to the Gold Charcoal Kiln",
			"Action": "EditData",
			"Target": "Data/Machines",
			"TargetField": [
				"(BC)nachonline.mps_GoldCharcoalKiln",
				"OutputRules"
			],
			"Entries": {
				"Lumisteria.MtVapius_CharcoalKilnRules": {
					"Id": "Lumisteria.MtVapius_CharcoalKilnRules",
					"Triggers": [
						{
							"RequiredItemId": "(O)Lumisteria.MtVapius_NightMiscanthus"
						}
					],
					"OutputItem": [
						{
							"ItemId": "(O)382",
							"MinStack": "{{G.C.K Driftwood to Coal Output}}",
							"StackModifiers": [
								{
									"Id": "DoubleSilverQuality",
									"Condition": "ITEM_QUALITY Input 1, !ITEM_QUALITY Input 2, RANDOM 0.1",
									"Modification": "Multiply",
									"Amount": 2.0
								},
								{
									"Id": "DoubleGoldQuality",
									"Condition": "ITEM_QUALITY Input 2, !ITEM_QUALITY Input 3, RANDOM 0.25",
									"Modification": "Multiply",
									"Amount": 2.0
								},
								{
									"Id": "DoubleIridiumQuality",
									"Condition": "ITEM_QUALITY Input 4, !ITEM_QUALITY Input 5, RANDOM 0.5",
									"Modification": "Multiply",
									"Amount": 2.0
								}
							],
							"StackModifierMode": "Stack"
						}
					],
					"MinutesUntilReady": 240
				}
			},
			"When": {
				"HasMod": "Lumisteria.MtVapius"
			}
		},
		{
			"LogName": "Add compatibility patch to the Diamond Charcoal Kiln",
			"Action": "EditData",
			"Target": "Data/Machines",
			"TargetField": [
				"(BC)nachonline.mps_DiamondCharcoalKiln",
				"OutputRules"
			],
			"Entries": {
				"Lumisteria.MtVapius_CharcoalKilnRules": {
					"Id": "Lumisteria.MtVapius_CharcoalKilnRules",
					"Triggers": [
						{
							"RequiredItemId": "(O)Lumisteria.MtVapius_NightMiscanthus"
						}
					],
					"OutputItem": [
						{
							"ItemId": "(O)382",
							"MinStack": "{{D.C.K Driftwood to Coal Output}}",
							"StackModifiers": [
								{
									"Id": "DoubleSilverQuality",
									"Condition": "ITEM_QUALITY Input 1, !ITEM_QUALITY Input 2, RANDOM 0.1",
									"Modification": "Multiply",
									"Amount": 2.0
								},
								{
									"Id": "DoubleGoldQuality",
									"Condition": "ITEM_QUALITY Input 2, !ITEM_QUALITY Input 3, RANDOM 0.25",
									"Modification": "Multiply",
									"Amount": 2.0
								},
								{
									"Id": "DoubleIridiumQuality",
									"Condition": "ITEM_QUALITY Input 4, !ITEM_QUALITY Input 5, RANDOM 0.5",
									"Modification": "Multiply",
									"Amount": 2.0
								}
							],
							"StackModifierMode": "Stack"
						}
					],
					"MinutesUntilReady": 240
				}
			},
			"When": {
				"HasMod": "Lumisteria.MtVapius"
			}
		},
		{
			"LogName": "Add compatibility patch to the Iridium Charcoal Kiln",
			"Action": "EditData",
			"Target": "Data/Machines",
			"TargetField": [
				"(BC)nachonline.mps_IridiumCharcoalKiln",
				"OutputRules"
			],
			"Entries": {
				"Lumisteria.MtVapius_CharcoalKilnRules": {
					"Id": "Lumisteria.MtVapius_CharcoalKilnRules",
					"Triggers": [
						{
							"RequiredItemId": "(O)Lumisteria.MtVapius_NightMiscanthus"
						}
					],
					"OutputItem": [
						{
							"ItemId": "(O)382",
							"MinStack": "{{I.C.K Driftwood to Coal Output}}",
							"StackModifiers": [
								{
									"Id": "DoubleSilverQuality",
									"Condition": "ITEM_QUALITY Input 1, !ITEM_QUALITY Input 2, RANDOM 0.1",
									"Modification": "Multiply",
									"Amount": 2.0
								},
								{
									"Id": "DoubleGoldQuality",
									"Condition": "ITEM_QUALITY Input 2, !ITEM_QUALITY Input 3, RANDOM 0.25",
									"Modification": "Multiply",
									"Amount": 2.0
								},
								{
									"Id": "DoubleIridiumQuality",
									"Condition": "ITEM_QUALITY Input 4, !ITEM_QUALITY Input 5, RANDOM 0.5",
									"Modification": "Multiply",
									"Amount": 2.0
								}
							],
							"StackModifierMode": "Stack"
						}
					],
					"MinutesUntilReady": 240
				}
			},
			"When": {
				"HasMod": "Lumisteria.MtVapius"
			}
		},
		{
			"LogName": "Add compatibility patch to the Radioactive Charcoal Kiln",
			"Action": "EditData",
			"Target": "Data/Machines",
			"TargetField": [
				"(BC)nachonline.mps_RadioactiveCharcoalKiln",
				"OutputRules"
			],
			"Entries": {
				"Lumisteria.MtVapius_CharcoalKilnRules": {
					"Id": "Lumisteria.MtVapius_CharcoalKilnRules",
					"Triggers": [
						{
							"RequiredItemId": "(O)Lumisteria.MtVapius_NightMiscanthus"
						}
					],
					"OutputItem": [
						{
							"ItemId": "(O)382",
							"MinStack": "{{R.C.K Driftwood to Coal Output}}",
							"StackModifiers": [
								{
									"Id": "DoubleSilverQuality",
									"Condition": "ITEM_QUALITY Input 1, !ITEM_QUALITY Input 2, RANDOM 0.1",
									"Modification": "Multiply",
									"Amount": 2.0
								},
								{
									"Id": "DoubleGoldQuality",
									"Condition": "ITEM_QUALITY Input 2, !ITEM_QUALITY Input 3, RANDOM 0.25",
									"Modification": "Multiply",
									"Amount": 2.0
								},
								{
									"Id": "DoubleIridiumQuality",
									"Condition": "ITEM_QUALITY Input 4, !ITEM_QUALITY Input 5, RANDOM 0.5",
									"Modification": "Multiply",
									"Amount": 2.0
								}
							],
							"StackModifierMode": "Stack"
						}
					],
					"MinutesUntilReady": 240
				}
			},
			"When": {
				"HasMod": "Lumisteria.MtVapius"
			}
		},
		{
			"LogName": "Add compatibility patch to the Prismatic Charcoal Kiln",
			"Action": "EditData",
			"Target": "Data/Machines",
			"TargetField": [
				"(BC)nachonline.mps_PrismaticCharcoalKiln",
				"OutputRules"
			],
			"Entries": {
				"Lumisteria.MtVapius_CharcoalKilnRules": {
					"Id": "Lumisteria.MtVapius_CharcoalKilnRules",
					"Triggers": [
						{
							"RequiredItemId": "(O)Lumisteria.MtVapius_NightMiscanthus"
						}
					],
					"OutputItem": [
						{
							"ItemId": "(O)382",
							"MinStack": "{{P.C.K Driftwood to Coal Output}}",
							"StackModifiers": [
								{
									"Id": "DoubleSilverQuality",
									"Condition": "ITEM_QUALITY Input 1, !ITEM_QUALITY Input 2, RANDOM 0.1",
									"Modification": "Multiply",
									"Amount": 2.0
								},
								{
									"Id": "DoubleGoldQuality",
									"Condition": "ITEM_QUALITY Input 2, !ITEM_QUALITY Input 3, RANDOM 0.25",
									"Modification": "Multiply",
									"Amount": 2.0
								},
								{
									"Id": "DoubleIridiumQuality",
									"Condition": "ITEM_QUALITY Input 4, !ITEM_QUALITY Input 5, RANDOM 0.5",
									"Modification": "Multiply",
									"Amount": 2.0
								}
							],
							"StackModifierMode": "Stack"
						}
					],
					"MinutesUntilReady": 240
				}
			},
			"When": {
				"HasMod": "Lumisteria.MtVapius"
			}
		},
	] 
}