{
	"Changes": [

	//Add Kohakutou
		{
            "Action": "EditData",
            "Target": "Data/Objects",
            "Entries": {		
				"miru.forestamber_EmeraldKohakutou": {
                    "Name": "miru.forestamber_EmeraldKohakutou",
                    "Displayname": "{{i18n:EmeraldKohakutou.name}}",
                    "Description": "{{i18n:EmeraldKohakutou.description}}",
                    "Type": "Basic",
                    "Category": -26,
                    "Price": 300,
                    "Texture": "Mods/miru.forestamber/Objects",
                    "SpriteIndex": 40,
                    "Edibility": 10,
					"ContextTags": [
						"color_green",
						"food_sweet"
					],
					
                },
				"miru.forestamber_AquamarineKohakutou": {
                    "Name": "miru.forestamber_AquamarineKohakutou",
                    "Displayname": "{{i18n:AquamarineKohakutou.name}}",
                    "Description": "{{i18n:AquamarineKohakutou.description}}",
                    "Type": "Basic",
                    "Category": -26,
                    "Price": 300,
                    "Texture": "Mods/miru.forestamber/Objects",
                    "SpriteIndex": 41,
                    "Edibility": 10,
					"ContextTags": [
						"color_aquamarine",
						"food_sweet"
					],
					
                },
				"miru.forestamber_RubyKohakutou": {
                    "Name": "miru.forestamber_RubyKohakutou",
                    "Displayname": "{{i18n:RubyKohakutou.name}}",
                    "Description": "{{i18n:RubyKohakutou.description}}",
                    "Type": "Basic",
                    "Category": -26,
                    "Price": 300,
                    "Texture": "Mods/miru.forestamber/Objects",
                    "SpriteIndex": 42,
                    "Edibility": 10,
					"ContextTags": [
						"color_red",
						"food_sweet"
					],
					
                },
				"miru.forestamber_AmethystKohakutou": {
                    "Name": "miru.forestamber_AmethystKohakutou",
                    "Displayname": "{{i18n:AmethystKohakutou.name}}",
                    "Description": "{{i18n:AmethystKohakutou.description}}",
                    "Type": "Basic",
                    "Category": -26,
                    "Price": 300,
                    "Texture": "Mods/miru.forestamber/Objects",
                    "SpriteIndex": 43,
                    "Edibility": 10,
					"ContextTags": [
						"color_purple",
						"food_sweet"
					],
					
                },
				"miru.forestamber_TopazKohakutou": {
                    "Name": "miru.forestamber_TopazKohakutou",
                    "Displayname": "{{i18n:TopazKohakutou.name}}",
                    "Description": "{{i18n:TopazKohakutou.description}}",
                    "Type": "Basic",
                    "Category": -26,
                    "Price": 300,
                    "Texture": "Mods/miru.forestamber/Objects",
                    "SpriteIndex": 44,
                    "Edibility": 10,
					"ContextTags": [
						"color_gold",
						"food_sweet"
					],
					
                },
				"miru.forestamber_JadeKohakutou": {
                    "Name": "miru.forestamber_JadeKohakutou",
                    "Displayname": "{{i18n:JadeKohakutou.name}}",
                    "Description": "{{i18n:JadeKohakutou.description}}",
                    "Type": "Basic",
                    "Category": -26,
                    "Price": 300,
                    "Texture": "Mods/miru.forestamber/Objects",
                    "SpriteIndex": 45,
                    "Edibility": 10,
					"ContextTags": [
						"color_jade",
						"food_sweet"
					],
					
                },
				
				//JewelKohakutou
				"miru.forestamber_JewelKohakutou": {
                    "Name": "miru.forestamber_JewelKohakutou",
                    "Displayname": "{{i18n:JewelKohakutou.name}}",
                    "Description": "{{i18n:JewelKohakutou.description}}",
                    "Type": "Basic",
                    "Category": -26,
                    "Price": 300,
                    "Texture": "Mods/miru.forestamber/Objects",
                    "SpriteIndex": 46,
					"ColorOverlayFromNextIndex":true,
                    "Edibility": 20,
					"ContextTags": [
						"color_gold",
						"food_sweet"
					],
					
                },
            },

		},
	]
}